Workbook

Sheet 01 - Préparation
C1: ACTIVITY | D1: TASK ID | E1: Resp. dept. | F1: ACTOR | G1: Status | H1: Duration | I1: Planned Start | J1: Planned End | K1: Dependency | L1: Comments
A2: Préparation
B3: Chapitre 1
C5: Livraison de la machine back end | F5: DI.VB | G5: Terminé | I5: 42614.375 | J5: 42614.708
C6: Ouverture 24/24 des locaux Valbonne | G6: N/A | I6: 42614.375 | J6: 42614.708
C7: Machine bis pour parallélisation des opérations d'export / Import. | F7: DI.VB | G7: Terminé | I7: 42614.375 | J7: 42614.708
C8: Recyclage des Traitements (BTCI et Les ALE) | G8: N/A | I8: 42614.375 | J8: 42614.708 | L8: PBED : Communication effectuée.
C9: Check connecteur adhésion (Loadbalancing) | E9: CC SAP | G9: Non commencé | I9: 42614.375 | J9: =I9 -> 42614.375 | L9: => si besoin demande ideal (demande de mep)
B13: Préparation autres | E13: DI.NR / AMO
C14: GO / NoGo sur lancement de l'upgrade | E14: DI.NR / AMO | G14: N/A | I14: 42620.625 | J14: 42620.708
C15: Communication indisponibilité eRH + backend | E15: DI.NR / AMO | G15: N/A
C16: Demande de mise en priorité 0 des jobs à partir de l'heure de la coupure | E16: DI.NR | G16: N/A
C17: Mise en priorité 0 des jobs à partir de l'heure de la coupure | E17: AOS | G17: N/A
C18: GO définitif du lancement de l'opération d'Upgrade | E18: DI.NR / AMO | G18: Non commencé
C19: Rappel de communication indisponibilité eRH + backend | E19: AMO | G19: N/A
C20: Prévenir l'équipe NewTest de l'indisponibilité des environnements | E20: DI.NR
A22: Upgrade détail dans onglet 02- Upgrade
B23: Preparation Online
C24: Vérifications Paramètres Oracle (dont shared_pool_size) | D24: 1 | E24: CGI | F24: David | G24: Passed | H24: 0.0069444444

Sheet 02 - Upgrade online
C1: ACTIVITY | D1: TASK ID | E1: Resp. dept. | F1: ACTOR | G1: Status | H1: Duration | I1: Planned Start | J1: Planned End | K1: Dependency | L1: Comments
A2: Upgrade online
B3: Préparation migration
C4: Vérifier la taille des file-systèms pour migration UNICODE | E4: DI.VB | F4: PA | G4: Terminé
C5: Vérifier les actions nécessaires à la sécurisation des interfaces | G5: Terminé
C6: EDI-> SAP stop l'envoie des photos | E6: EDIGRAPH | F6: Théo/Nathalie Guédeu | G6: Terminé | H6: 1.0069444 | I6: 42618.375 | J6: 42618.708
C7: MOS doit couper MOSREAL en entrant (delta) | E7: ELEARNING | F7: Thu-Cam/Kim | G7: Terminé | H7: 1.0069444 | I7: 42618.375 | J7: 42618.708
C8: (interface reception avances caisses) Laurence KARAS doit bloquer les avances pour ne pas executer le traitement sinon fichiers écrasés | E8: RDJ | F8: Geneviève/ Laurence KARAS | G8: Terminé | H8: 1.0069444 | I8: 42618.375 | J8: 42618.708
C9: Augmenter la profondeur à xj? | E9: ROSTER | F9: Sandrine/ | G9: Terminé | H9: 1.0069444 | I9: 42618.375 | J9: 42618.708
C10: Message sur intralignes | F10: Sophie /? | G10: Terminé | I10: 42618.375 | J10: 42618.708
C11: Message sur e-services | F11: Sophie /? | G11: Terminé | I11: 42618.375 | J11: 42618.708
C12: Passer la durée de retention des backups Oracle à 10 | E12: DI.VB | F12: SP | G12: Terminé | L12: 30/08 PA
B13: Preparation Online
C14: Rollback - Switch archivelog + identification du dernier numéro du journal de log | D14: 1 | E14: DI.VB | F14: PA | G14: Terminé | H14: 0.0069444444 | I14: 42618.375 | J14: =I14+H14 -> 42618.382 | L14: Dernier numéro archivelog : 118 401 sur PRH
C15: Rollback - Activation du RSYNC (périodicité 10 mins) | D15: 1 | E15: DI.VB | F15: PA | G15: Terminé | H15: 0.0069444444 | I15: =J14 -> 42618.382 | J15: =I15+H15 -> 42618.389 | L15: Sauvegarde du répertoire /sapsum tout au long de l'upgrade
C16: Rollback - Sauvegarde de l'état hors BDD | D16: 1 | E16: CGI | F16: David | G16: Terminé | H16: 0.020833333 | I16: =J15 -> 42618.389 | J16: =I16+H16 -> 42618.41
C17: Vérifications Paramètres Oracle (dont shared_pool_size) | D17: 1 | E17: CGI | F17: David | G17: Terminé | H17: 0.0069444444 | I17: 42618.417 | J17: =I17+H17 -> 42618.424
C18: MAJ des statistiques | D18: 2 | E18: CGI | F18: David | G18: Terminé | H18: 0.041666667 | I18: =+J17 -> 42618.424 | J18: =I18+H18 -> 42618.465 | L18: Durée estimée 20 minutes mais temps réel 2 heures
C19: Vérification des tables cluster | D19: 3 | E19: CGI | F19: David | G19: Terminé | H19: 0.0034722222 | I19: =+J18 -> 42618.465 | J19: =I19+H19 -> 42618.469
C20: /ASU/UPGRADE | D20: 4 | E20: CGI | F20: David | G20: Terminé | H20: 0.010416667 | I20: =+J19 -> 42618.469 | J20: =I20+H20 -> 42618.479 | L20: Problème d'import de l'OT DVHK960015 BC - UPG - OSS 2021095 - CUSTOMER MODIFICATION Contient et des données et du dev. Voir avec Emmanuel sur split d'OT ou repassager de celui-ci. Identifier quand repasser l'OT
C21: Sauvegarde BDD [?] | D21: 5 | E21: CGI | F21: David | G21: Terminé | H21: 0.0034722222 | I21: =+J20 -> 42618.479 | J21: =I21+H21 -> 42618.483 | L21: Sauvegarde automatique au fil de l'eau
C22: Augmentation Tablespace PSAPTEMP | D22: 6 | E22: CGI | F22: David | G22: Terminé | H22: 0.0034722222 | I22: =+J21 -> 42618.483 | J22: =I22+H22 -> 42618.486 | L22: Suite aux retours d’expérience DR1 et DR2, nous augmentons les tablespaces suivants : - PSAPSR3 (+100 Go) en auto - SYSTEM (+1024 Mo) en auto (taille max fichier 2 Go, fichier min 1024Go, un pas de 200m) - PSAPUNDO (+ 2Go) pas d’auto
C23: Augmentation et Création Tablespaces Upgrade | D23: 7 | E23: CGI | F23: David | G23: Terminé | H23: 0.010416667 | I23: =+J22 -> 42618.486 | J23: =I23+H23 -> 42618.497 | L23: Création du tablespaces PSAPSR3740 - PSAPSR3740 (137 Go) en auto
C24: Vérification Utilisation Client Oracle 11 | D24: 9 | E24: CGI | F24: David | G24: Terminé | H24: 0.0069444444 | I24: =J23 -> 42618.497 | J24: =I24+H24 -> 42618.503 | L24: Adaptation par lien
C25: Contrôle Taille RedoLog | D25: 10 | E25: CGI | F25: David | G25: Terminé | H25: 0.0034722222 | I25: =+J24 -> 42618.503 | J25: =I25+H25 -> 42618.507 | L25: La taille ne sera pas modifiée. Stratégie brconnect privlégiée : il s'agit de déplacer les logs qui ont atteint leur taille max immédiatement sur un autre serveur pour ne pas saturer le dossier /oracle/orarch
C26: SE14 -> ordre de DB -> Traitement en masse | D26: 11 | E26: CGI | F26: David | G26: Terminé | H26: 0.0034722222 | I26: =J24 -> 42618.503 | J26: =I26+H26 -> 42618.507
C27: Contrôle TATGPC et TATGPCA (vides) | D27: 12 | E27: CGI | F27: David | G27: Terminé | H27: 0.0034722222 | I27: =J26 -> 42618.507 | J27: =I27+H27 -> 42618.51 | L27: Les tables sont vides
C28: SP12 : Supprimer les inconsistances de la TEMSE | D28: 13 | E28: CGI | F28: David | G28: Terminé | H28: 0.0034722222 | I28: =J27 -> 42618.51 | J28: =I28+H28 -> 42618.514
C29: SM13 : Supprimer les updates en erreur | D29: 14 | E29: CGI | F29: David | G29: Terminé | H29: 0.0034722222 | I29: =J28 -> 42618.514 | J29: =I29+H29 -> 42618.517
C30: DB02 : Comparer SAP DDIC et Oracle DDIC | D30: 15 | E30: CGI | F30: David | G30: Terminé | H30: 0.0034722222 | I30: =J28 -> 42618.514 | J30: =I30+H30 -> 42618.517 | L30: Pas d'inconsistence
C31: Lancer BRARCHIVE au fil de l'eau | D31: 15 | E31: CGI | F31: David | G31: Terminé | H31: 0.0034722222 | I31: =J29 -> 42618.517 | J31: =I31+H31 -> 42618.521 | L31: Etape supplémentaire rajoutée et demandée par Air France 30/08 PA : Lancer une copie de brarchive depuis /tmp
B32: Upgrade Online | I32: =J31 -> 42618.521 | J32: =I32+H32 -> 42618.521
C33: SUM - Initialisation | D33: 20 | E33: CGI | F33: David | G33: Terminé | H33: 0.020833333 | I33: =J31+0.08 -> 42618.601 | J33: =I33+H33 -> 42618.622
C34: SUM - Extraction | D34: 30 | E34: CGI | F34: David | G34: Terminé | H34: 0.0034722222 | I34: =J33 -> 42618.622 | J34: =I34+H34 -> 42618.625
C35: PREP_EXTRACT (Extraction) | D35: 31 | E35: CGI | F35: David | G35: Terminé | H35: 0.0034722222 | I35: =J34 -> 42618.625 | J35: =I35+H35 -> 42618.629
C36: PREP_PRE_CHECK (Checks the system status) | D36: 32 | E36: CGI | F36: David | G36: Terminé | H36: 0.0069444444 | I36: =J35 -> 42618.629 | J36: =I36+H36 -> 42618.636
C37: PREP_INPUT_CHECK (Parameter input) | D37: 33 | E37: CGI | F37: David | G37: Terminé | H37: 0.013888889 | I37: =+J36 -> 42618.636 | J37: =I37+H37 -> 42618.649
C38: PREP_INIT (Initialization) | D38: 34 | E38: CGI | F38: David | G38: Terminé | H38: 0.017361111 | I38: =+J37 -> 42618.649 | J38: =I38+H38 -> 42618.667
C39: PREP_IMPORT (Import) | D39: 35 | E39: CGI | F39: David | G39: Terminé | H39: 0.0069444444 | I39: =+J38 -> 42618.667 | J39: =I39+H39 -> 42618.674
C40: PREP_PARSETUP (Setup parameters for tool) | D40: 36 | E40: CGI | F40: David | G40: Terminé | H40: 0.0069444444 | I40: =+J39 -> 42618.674 | J40: =I40+H40 -> 42618.681
C41: RSECSSFS | D41: 37 | E41: CGI | F41: David | G41: Terminé | H41: 0.010416667 | I41: =+J40 -> 42618.681 | J41: =I41+H41 -> 42618.691 | L41: - Restes de SPDD - SPAU > étape ignorée à cet instant
C42: Backup des Wage Types | D42: 38 | E42: CGI | F42: David | G42: Terminé | H42: 0.0034722222 | I42: =+J41 -> 42618.691 | J42: =I42+H42 -> 42618.695
C43: Vérifier la table COKEY2 | D43: 39 | E43: CGI | F43: David | G43: Terminé | H43: 0.0034722222 | I43: =+J42 -> 42618.695 | J43: =I43+H43 -> 42618.698
C44: SUM - Configuration | D44: 40 | E44: CGI | F44: David | G44: Terminé | H44: 0.0034722222 | I44: =J43 -> 42618.698 | J44: =I44+H44 -> 42618.702
C45: PREP_CONFIGURATION (Configuration and language selection) | D45: 41 | E45: CGI | F45: David | G45: Terminé | H45: 0.017361111 | I45: =+J44 -> 42618.702 | J45: =I45+H45 -> 42618.719
C46: PREP_SETUP (Setup control data) | D46: 42 | E46: CGI | F46: David | G46: Terminé | H46: 0.0034722222 | I46: =+J45 -> 42618.719 | J46: =I46+H46 -> 42618.722
C47: PREP_EXTENSION (Extension module) | D47: 43 | E47: CGI | F47: David | G47: Terminé | H47: 0.055555556 | I47: =+J46 -> 42618.722 | J47: =I47+H47 -> 42618.778 | L47: - Le package ST-PI et ses SPs étaient manquants en EPS/in - La partie PREP_EXTENSION/CONFLICT_CHECK dure à elle seule environ 35 mins
C48: PREP_INTEGRATION (Integration) | D48: 44 | E48: CGI | F48: David | G48: Terminé | H48: 0.010416667 | I48: =J47+0.6 -> 42619.378 | J48: =I48+H48 -> 42619.388
C49: SUM - Checks | D49: 50 | E49: CGI | F49: David | G49: Terminé | H49: 0.0034722222 | I49: =+J48 -> 42619.388 | J49: =I49+H49 -> 42619.392 | L49: Création de la shadow instance Mot de passe provisoire utilisé (sup. 8 caractères) : CGIcg!2016
C50: PREP_SPACECALC (Space calculations) | D50: 51 | E50: CGI | F50: David | G50: Terminé | H50: 0.010416667 | I50: =+J49 -> 42619.392 | J50: =I50+H50 -> 42619.402
C51: PREP_GENCHECKS (General checks) | D51: 52 | E51: CGI | F51: David | G51: Terminé | H51: 0.013888889 | I51: =+J50 -> 42619.402 | J51: =I51+H51 -> 42619.416 | L51: - Importer les Ots DVHK960007 et DVHK960090 pour corriger les erreurs dans la SUM
C52: PREP_PREPROC (Preliminary upgrade processing) | D52: 53 | E52: CGI | F52: David | G52: Terminé | H52: 0.024305556 | I52: =+J51 -> 42619.416 | J52: =I52+H52 -> 42619.44 | L52: - A prendre en compte également le temps pour augmenter les tablespaces aux tailles exigées par SAP pour PSAPSR3(+100 Go), SYSTEM (+1024 Mo), PSAPUNDO (800 Mo), et création du tablespace PSAPSR3740 (137 Go). En production, à faire avant la SUM NB. PSAPSR3640 est conservé pour le moment.
C53: Renumérotation SPROXXSL et SPROXXSL~ | D53: 54 | E53: CGI | F53: David | G53: Terminé | H53: 0.0034722222 | I53: =+J52 -> 42619.44 | J53: =I53+H53 -> 42619.444 | L53: Fait mais 0 ligne affectée pour chaque requête SQL - A repasser si l'erreur associée se produit.
C54: SUM - Preprocessing | D54: 60 | E54: CGI | F54: David | G54: Terminé | H54: 0.0034722222 | I54: =J53 -> 42619.444 | J54: =I54+H54 -> 42619.447
C55: MAIN_INIT (Configuration and Initialization) | D55: 61 | E55: CGI | F55: David | G55: Terminé | H55: 0.0020833333 | I55: =+J54 -> 42619.447 | J55: =I55+H55 -> 42619.449
C56: MAIN_SHDCRE (Import and Modification Transfer) | D56: 62 | E56: CGI | F56: David | G56: Terminé | H56: 0.041666667 | I56: =J55 -> 42619.449 | J56: =I56+H56 -> 42619.491 | L56: Import de l'OT de correction DVMK900588 - M-RH_GA-IM02303592-Remise à niveau IBAN-01 sur PRH à 10h30
C57: MAIN_SHDINST (Shadow System Installation) | D57: 63 | E57: CGI | F57: David | G57: Terminé | H57: 0.0013888889 | I57: =J56 -> 42619.491 | J57: =I57+H57 -> 42619.492
C58: MAIN_SHDPREPUT (Shadow System Operations: Preput) | D58: 64 | E58: CGI | F58: David | G58: Terminé | H58: 0.020138889 | I58: =+J57 -> 42619.492 | J58: =I58+H58 -> 42619.513
C59: Notifier DI.VB du début de la phase MAIN_SHDRUN | E59: DI.VB | F59: SP | G59: Terminé | H59: 0 | I59: =J58 -> 42619.513 | J59: =I59+H59 -> 42619.513 | L59: 30/08 PA : lancement manuel d'une full online 06/09: Lancée par AirFrance à 13:08
C60: MAIN_SHDRUN (Shadow System Operations: SPDD and Activation) | D60: 65 | E60: CGI | F60: David/Emmanuel | G60: Terminé | H60: 0.375 | I60: =+J58 -> 42619.513 | J60: =I60+H60 -> 42619.888 | L60: MIHA 12/08 : Zone commentaires : remplacer les 'QSH' par 'PPH' '- 'L'OT DVHK960018 ne contient pas tous les objets à ajuster en PPH > Option 'Yes, with double check' : Les ajustements manquants se feront ultérieurement sur le système OT - Création du user SPDDADM (copie de DDIC en PPH_000 sur shadow instance) - Ajustement objets en SPDD sur PPH par ELAIR avec l'OT DVHK960007 et DVHK960090
C61: Notifier DI.VB de la fin de la phase MAIN_SHDRUN | E61: DI.VB | F61: SP | G61: Terminé | H61: 0.0034722222 | I61: =J60 -> 42619.888 | J61: =I61+H61 -> 42619.891 | L61: 30/08 PA : vérification de la fin du backup + début de restore de la full sur UCH 06/09 : Restauration en cours de la BDD sur serveur source qvipsapauh02 depuis 17h
C62: MAIN_SHDIMP (Shadow Import) | D62: 66 | E62: CGI | F62: David | G62: Terminé | H62: 0.25555556 | I62: =J60+0.5 -> 42620.388 | J62: =I62+H62 -> 42620.643 | L62: Attendre que les jobs suivants se terminent avant de valider l'entrée en phase de Downtime (SM37) -CRR_OPERATION -RSUPG_ISU_CRR
C63: MAIN_DTTRANS (Transition to Downtime for Downtime-minimized) | D63: 67 | E63: CGI | F63: David | G63: Non commencé | H63: 0.0020833333 | I63: 42621.75 | J63: =I63+H63 -> 42621.752 | L63: Ne pas lancer l'action avant le GO pour downtime
A64: Upgrade dowtime Détail dans Onglet 02'- Export - Import
B65: Préparation dowtime Air France | I65: =#REF! -> #REF! | J65: =I65+H65 -> #REF!
C66: Cf onglet 02'

Sheet 02' - Upgrade dowtime
C1: ACTIVITY | D1: TASK ID | E1: Resp. dept. | F1: ACTOR | G1: Status | H1: Duration | I1: Planned Start | J1: Planned End | K1: Dependency | L1: Comments
A2: Upgrade dowtime
B3: Préparation Dowtime équipe fonctionnelle | I3: =#REF! -> #REF! | J3: =I3+H3 -> #REF!
C4: Vérifier que la mise à jour des OCAB (until & Except) dans l'ordonnanceur a été faite | E4: DI.NR | G4: Terminé | I4: 42613.375 | J4: 42621.5
C5: DINR Vérifier que le traitement est bien passé à 1h le jeudi matin pré upgrade | E5: FAST (Ancienneté PN) | F5: Sandrine | G5: Terminé | H5: 0.0069444444 | I5: 42621.375 | J5: 42621.5
C6: modifier variante d'extraction la veille sur 2 interfaces (inscription + session) | E6: GECO SF | F6: Thu-Cam | G6: Terminé | H6: 0.0069444444 | I6: 42621.375 | J6: 42621.5
C7: Prévenir Que les sondes IP label seront en erreur sur la production PRH. | E7: DI.NR | G7: Terminé | H7: 0.0069444444 | I7: 42621.375 | J7: 42621.5
B8: Go / No Go | I8: =#REF! -> #REF! | J8: =I8+H8 -> #REF!
C9: Dernier Go nogo | G9: Non commencé | H9: 0.0069444444 | I9: 42621.708 | J9: =I9+H9 -> 42621.715
B11: Préparation dowtime Air France | I11: =#REF! -> #REF! | J11: =I11+H11 -> #REF!
C12: Paramétrer le message d'information sur coupure à 17 h des systèmes | E12: CC SAP | F12: Julien | G12: Terminé | H12: 0.041666667 | I12: 42621.583 | J12: =I12+H12 -> 42621.625 | L12: PBED 22/8 : Tache ajoutée
C13: Vérifier l'arret des envois de fichiers des partenaires | E13: DI.NR | F13: Geneviève, Thu Cam et Sandrine | G13: Terminé | H13: 0.083333333 | I13: 42621.583 | J13: =I13+H13 -> 42621.667 | L13: PBED 22/8 : Tache ajoutée
C14: Vérifier qu'il n'y a plus de BTCI en erreur à recycler | E14: DI.NR | F14: AMO | G14: Terminé | H14: 0.083333333 | I14: 42621.583 | J14: =I14+H14 -> 42621.667 | L14: PBED 22/8 : Tache ajoutée
C15: Blocage des utilisateurs sauf technique et liste donné par le projet (JCO_EP_XSS, UWLSERVICES) | D15: 71 | E15: CC SAP | F15: JBE | G15: Terminé | H15: 0.020833333 | I15: 42621.708 | J15: =I15+H15 -> 42621.729 | L15: Sur PPH, blocage en plus de la EWZ5 les users suivants : CRYSTAL GUSUSER MATIS_SOA TWS M135586 Et débloqué : DTRAN T021131 STPIGLI FRBAUDINAUD PAANDRE ADMIN MAESTRO COREALE HRALE
C16: Déconnexion des users encore connectés | D16: 72 | E16: CC SAP | F16: JBE | G16: Terminé | H16: 0.020833333 | I16: 42621.708 | J16: =I16+H16 -> 42621.729
C17: Arrêt d'alimentation d'interface autre que par TWS : blocage du job d'envoi IDOC de Corporate vers HR (désactivation du partenaire logique PRH200 sur Corporate PRD 200) | D17: 69 | E17: CC SAP | F17: JBE | G17: Terminé | H17: 0.0069444444 | I17: =J16 -> 42621.729 | J17: =I17+H17 -> 42621.736 | L17: Modification du libellé
C18: Arrêt des services Adhesion sur HRCI-AF | D18: 68 | E18: CC SAP | F18: JBE | G18: Terminé | H18: 0.0069444444 | I18: =J17 -> 42621.736 | J18: =I18+H18 -> 42621.743
C19: Blocage des utilisateurs MAESTRO et *ALE | D19: 76 | E19: CC SAP | F19: JBE | G19: Terminé | H19: 0.0069444444 | I19: =J18 -> 42621.743 | J19: =I19+H19 -> 42621.75 | L19: Sur PPH : Reblocage de COREALE, HRALE, MAESTRO
C20: Suspension des jobs SAP | D20: 70 | E20: CC SAP | F20: JBE | G20: Terminé | H20: 0.0034722222 | I20: =J19 -> 42621.75 | J20: =I20+H20 -> 42621.753
C21: Arrêt de l'envoi des fichiers de timeport | D21: 68 | E21: DINR 1C | F21: Nathalie GUEDEU | G21: Terminé | H21: 0.0069444444 | I21: =I15 -> 42621.708 | J21: =I21+H21 -> 42621.715
C22: Redirection URL Portail vers nouvelle production portail | E22: Support | G22: Terminé | H22: 0.010416667 | I22: =J16 -> 42621.729 | J22: =I22+H22 -> 42621.74
C23: Test d'accès nouveau portail (intranet et internet) | E23: CC SAP | F23: JBE | G23: Terminé | H23: 0.010416667 | I23: =J22 -> 42621.74 | J23: =I23+H23 -> 42621.75 | L23: KHAZ 23/08
C24: Redirection URL Portail vers page de maintenance | E24: Support | G24: Terminé | H24: 0.0034722222 | I24: =J23 -> 42621.75 | J24: =I24+H24 -> 42621.753 | L24: KHAZ 23/08 : Go doit être donné par Julien
C25: Arrêt du portail | D25: 73 | E25: DI.VB | F25: JBE | G25: Terminé | H25: 0.0034722222 | I25: =J24 -> 42621.753 | J25: =I25+H25 -> 42621.757 | L25: 30/08 PA : arret des deux portails (PW1old et new) désactiver les template des process SAP freeze des clusters
C26: Vérification de la fin des interfaces en cours :
C27: Envoi du fichier via flux RVGN85 [GPN, CREW -> Données administratives] Le fichier doit arriver avant 17h15 pour être intégré | E27: GPN | F27: Pavel | G27: Terminé | H27: 0.010416667 | I27: 42621.698 | J27: =I27+H27 -> 42621.708
C28: Envoi du fichier via flux RVGN85 [GPN, CREW -> Données administratives] Le fichier doit arriver avant 17h15 pour être intégré | E28: INTRAPN (CREW) | F28: Pavel | G28: Terminé | H28: 0.010416667 | I28: 42621.698 | J28: =I28+H28 -> 42621.708
C29: Envoi du fichier via flux RVGN85 [GPN, CREW -> Données administratives] Le fichier doit arriver avant 17h15 pour être intégré | E29: EDITO | F29: Pavel | G29: Terminé | H29: 0.010416667 | I29: 42621.698 | J29: =I29+H29 -> 42621.708
C30: Envoi du fichier via flux RVGN85 [GPN, CREW -> Données administratives] Le fichier doit arriver avant 17h15 pour être intégré | E30: IBPN | F30: Pavel | G30: Terminé | H30: 0.010416667 | I30: 42621.698 | J30: =I30+H30 -> 42621.708
C31: Envoi du fichier via flux RVGN85 [GPN, CREW -> Données administratives] Le fichier doit arriver avant 17h15 pour être intégré | E31: CIRCPN (CIRCUIT PN) | F31: Pavel | G31: Terminé | H31: 0.010416667 | I31: 42621.698 | J31: =I31+H31 -> 42621.708
C32: Envoi du fichier via flux RVGN85 [GPN, CREW -> Données administratives] Le fichier doit arriver avant 17h15 pour être intégré | E32: FRIENDLY | F32: Pavel | G32: Terminé | H32: 0.010416667 | I32: 42621.698 | J32: =I32+H32 -> 42621.708
C33: Envoi du fichier via flux RVGN86 [ICART - > Données administratives] | E33: ICART | F33: Pavel | G33: Terminé | H33: 0.010416667 | I33: 42621.698 | J33: =I33+H33 -> 42621.708
C34: Appeler le support pour suspendre TWS (FENCE) | E34: DINR | F34: Théo | G34: Terminé | H34: 0.010416667 | I34: =I33+2 -> 42623.698 | J34: =I34+H34 -> 42623.708
C35: Suspension des jobs TWS (type SAP et Unix) | D35: 77 | E35: Support | G35: Terminé | H35: 0.010416667 | I35: 42621.719 | J35: =I35+H35 -> 42621.729 | L35: PBED 22/8 : Tache ajoutée
C36: Appeler le support pour suspendre TWS | E36: DINR | F36: Théo | G36: Terminé | H36: 0.010416667 | I36: =J33 -> 42621.708 | J36: =I36+H36 -> 42621.719
C37: Arrêt des flux (vers lh-pprh01-ci) avant l'arrêt de la machine SAP | D37: 2 | E37: AOS flux | F37: Marc Amaury SALMON | G37: Terminé | H37: 0.010416667 | I37: 42621.719 | J37: =I37+H37 -> 42621.729 | L37: Vérifier l'heure de demande (de préférence 1h avant)
C38: Controler le Fence = 101 (TWS) | E38: DI.NR | F38: Pavel | G38: Terminé | H38: 0.0069444444 | I38: =J37 -> 42621.729 | J38: =I38+H38 -> 42621.736
C39: Création des Ots de sauvegarde des données Hercule (custo + HRP1601) | D39: 75 | E39: CGI | F39: Julien | G39: Terminé | H39: 0.010416667 | I39: =J25 -> 42621.757 | J39: =H39+I39 -> 42621.767 | L39: Créer 3 Ots dans l'environnement source : PRHK900142 PRHK900141 PRHK900140 PRHK900139 et les libérer Demander la création des Ots à Julien par FDS
B40: Upgrade Downtime | I40: =+#REF! -> #REF! | J40: =I40+H40 -> #REF!
C41: Check Sauvegarde FULL | D41: 80 | E41: DI.VB | F41: PA/SP | G41: Terminé | H41: 0.0069444444 | I41: 42621.729 | J41: =I41+H41 -> 42621.736 | L41: 30/08 PA : AF doit s'assurer de l'existence d'une sauvegarde FULL au milieu de la Shadow Import pour faire les restore sur UCH
C42: Rolback fichiers | E42: CGI | F42: ? | G42: Terminé | H42: 0.0069444444 | I42: =J28 -> 42621.708 | J42: =J28 -> 42621.708 | L42: 30/08 PA : CGI doit expliciter la procédure de rollback
C43: switch Archivelog + BRARCHIVE | D43: 80 | E43: DI.VB | F43: PA/SP | G43: Terminé | H43: 0.0069444444 | I43: =J41 -> 42621.736 | J43: =I43+H43 -> 42621.743 | L43: 30/08 PA : noter le numéro de séquence pour rolback 09/09 - Numéro de séquence 119732
A44: 70 | C44: Arrêt du Rsync /sapsum périodique et lancement Rsync en mode manuel | D44: 81 | E44: DI.VB | F44: PA | G44: Terminé | H44: 0.0034722222 | I44: =J43 -> 42621.743 | J44: =I44+H44 -> 42621.747 | L44: 30/08 PA : Freeze cluster etc
C45: SUM - Execution (Downtime)
C46: Sauvegarde SUM + Fichiers de profile + variables d'environnement .dbenv et .sapenv | D46: 83 | E46: CGI | G46: Terminé | H46: 0.020833333 | I46: =J44 -> 42621.747 | J46: =I46+H46 -> 42621.767 | L46: 30/08 PA : Expliciter la procedure de Rollback Commentaire nitial : La sauvegarde des binaires/profiles + variables d'environnement a été faite en avance de phase pour le DR2
C47: MAIN_DTTRANS (Transition to Downtime for Downtime-minimized) | D47: 67 | E47: CGI | F47: David | G47: Terminé | H47: 0.0020833333 | I47: =J46 -> 42621.767 | J47: =I47+H47 -> 42621.769 | L47: Ne pas lancer l'action avant le GO pour downtime
C48: MAIN_SWITCH (Downtime I: Switch tables and Kernel) | D48: 84 | E48: CGI | F48: David | G48: Terminé | H48: 0.0097222222 | I48: =J47 -> 42621.769 | J48: =I48+H48 -> 42621.779 | L48: Un problème lié au message server qui ne démarrait plus du tout à retarder cette phase. Un reboot du serveur était necessaire.
C49: MAIN_NEWBAS (Downtime II: Conversion, Main Import, XPRAs) | D49: 85 | E49: CGI | F49: David | G49: Terminé | H49: 0.083333333 | I49: =J48 -> 42621.779 | J49: =I49+H49 -> 42621.863 | L49: 1 heure d'avance en terme de traitement (2h au lieu de 3)
C50: MAIN_UPTRANS (Transition to uptime) | D50: 86 | E50: CGI | F50: David | G50: Terminé | H50: 0.0013888889 | I50: =+J49 -> 42621.863 | J50: =I50+H50 -> 42621.864
C51: SUM - Postprocessing
C52: MAIN_POSTPROC (Post Processing) | D52: 88 | E52: CGI | F52: David | G52: Terminé | H52: 0.010416667 | I52: =J50 -> 42621.864 | J52: =I52+H52 -> 42621.874 | L52: SPAU : derniers ajustements à réaliser en parallèle Penser à donner les droits suffisants à SPAU-SPDD pour le chantier DEV sur les environnements 08/09 - Problème de nombre de process batch : la configuration n'était pas chargée en RZ10 et RZ04. | O52: Est-ce que cela ne nécessiterait pas une action supplémentaire?
C53: MAIN_POSTCLEAN (Final cleanup) | D53: 89 | E53: CGI | F53: David | G53: Terminé | H53: 0.125 | I53: =+J52 -> 42621.874 | J53: =I53+H53 -> 42621.999 | L53: Attention, le nombre de process Batch doit être mis à 5 minimum en RZ04 en cas d'erreur (problème rencontré sur DVH et QSH uniquement pour le moment) | O53: Est-ce que cela ne nécessiterait pas une action supplémentaire?
C54: Post-Opérations | D54: 90 | E54: CGI | F54: David | G54: Terminé | H54: 0.0034722222 | I54: =+J53 -> 42621.999 | J54: =I54+H54 -> 42622.003
C55: Import des Ots Hercules (un par un) | D55: 91 | E55: CGI | F55: David | G55: Terminé | H55: 0.0034722222 | I55: =+J54 -> 42622.003 | J55: =I55+H55 -> 42622.006 | L55: A importer un par un : - DVHK955110 - DVHK960027 - DVHK955110 - DVHK955108 A importer en même temps : (prendre les nouveaux OTs de Julien) PRHK900142 PRHK900141 PRHK900140 PRHK900139

Sheet 03 - Export - Import
C1: ACTIVITY | D1: TASK ID | E1: Resp. dept. | F1: ACTOR | G1: Status | H1: Duration | I1: Planned Start | J1: Planned End | K1: Dependency | L1: Comments
A2: Export - Import
B3: Preparation Unicode
C4: Rollback - Sauvegarde Incrémentale Online | D4: 1 | E4: DI.VB | F4: SP | G4: Terminé | H4: 0.020833333 | I4: ='02'' - Upgrade dowtime'!J55 -> 42622.006 | J4: =I4+H4 -> 42622.027 | L4: A faire au moins une fois durant la préparation Unicode
C5: Lancement des statistiques Oracle | D5: 1 | E5: CGI | F5: David | G5: Terminé | H5: 0.027777778 | I5: =J4 -> 42622.027 | J5: =I5+H5 -> 42622.055 | L5: Un problème de privilège s'est produit avant l'exécution de brconnect. La commande pour résoudre est indiquée dans le CR
C6: Notifier DI.VB de lancer le Back up online INCR | D6: 14 | E6: DI.VB | F6: SP | G6: Terminé | H6: 0.0069444444 | I6: =J5 -> 42622.055 | J6: =I6+H6 -> 42622.062 | L6: 30/08 PA
C7: Lancement du report RPUMKG00 | D7: 3 | E7: CGI | F7: Pierre | G7: Terminé | H7: 0.0034722222 | I7: =J6 -> 42622.062 | J7: =I7+H7 -> 42622.065
C8: Lancement du report SMIGR_CREATE_DDL | D8: 4 | E8: CGI | F8: Pierre | G8: Terminé | H8: 0.0034722222 | I8: =J7 -> 42622.065 | J8: =I8+H8 -> 42622.069
C9: Recharger les Wage Types | D9: 5 | E9: CGI | F9: Pierre | G9: Terminé | H9: 0.0034722222 | I9: =J8 -> 42622.069 | J9: =I9+H9 -> 42622.072
C10: Unicode dans les programmes générés | D10: 6 | E10: CGI | F10: Pierre | G10: Terminé | H10: 0.0034722222 | I10: =J9 -> 42622.072 | J10: =I10+H10 -> 42622.076
C11: SE14 - Suppression des tables temporaires invalides | D11: 7 | E11: CGI | F11: Pierre | G11: Terminé | H11: 0.0034722222 | I11: =J10 -> 42622.076 | J11: =I11+H11 -> 42622.079
C12: Notifier DI.VB de restorer le Back up online INCR sur UCH | D12: 14 | E12: DI.VB | F12: SP | G12: Terminé | H12: 0.0034722222 | I12: =J11 -> 42622.079 | J12: =I12+H12 -> 42622.083 | L12: 30/08 PA
C13: SPUMG - #1 | D13: 8 | E13: CGI | F13: Pierre | G13: Terminé | H13: 0.020833333 | I13: =J12 -> 42622.083 | J13: =I13+H13 -> 42622.103
C14: Vider les tables DDNTF_CONV_UC et DDNTT_CONV_UC | D14: 9 | E14: CGI | F14: Pierre | G14: Terminé | H14: 0.0034722222 | I14: =J13 -> 42622.103 | J14: =I14+H14 -> 42622.107
C15: SPUMG - #2 - Création Unicode Nametabs | D15: 10 | E15: CGI | F15: Pierre | G15: Terminé | H15: 0.12847222 | I15: =J14 -> 42622.107 | J15: =I15+H15 -> 42622.235 | L15: Attention, opération lancée plusieurs fois sur QSH.
C16: SPUMG - #3 - Additional Downtime Steps | D16: 11 | E16: CGI | F16: Pierre | G16: Terminé | H16: 0.0027777778 | I16: =J15 -> 42622.235 | J16: =I16+H16 -> 42622.238
C17: Sauvegarde des log de Jobs ABAP | D17: 12 | E17: CGI | F17: Pierre | G17: Terminé | H17: 0.0034722222 | I17: =J16 -> 42622.238 | J17: =I17+H17 -> 42622.242
C18: Vérifier shmmax | D18: 13 | E18: CGI | F18: Pierre | G18: Terminé | H18: 0.00069444444 | I18: =J17 -> 42622.242 | J18: =I18+H18 -> 42622.242 | L18: A faire sur les 8 AS
C19: Sur validation CGI, restoration des journaux oracle et ouverture de UCH | D19: 14 | E19: DI.VB | F19: SP | G19: Terminé | H19: 0.036805556 | I19: =J18 -> 42622.242 | J19: =I19+H19 -> 42622.279 | L19: 30/08 PA
B20: Export | I20: =#REF! -> #REF! | J20: =I20+H20 -> #REF!
C21: Configuration du SAP Distribution Monitor | G21: Terminé
C22: Scripts d’environnement pour export et import | D22: 21 | E22: CGI | F22: Pierre | G22: Terminé | H22: 0.0069444444 | I22: 42621.625 | J22: =I22+H22 -> 42621.632 | L22: Action anticipée
C23: Paramétrage distribution_monitor_cmd.properties | D23: 22 | E23: CGI | F23: Pierre | G23: Terminé | H23: 0.0069444444 | I23: =J22 -> 42621.632 | J23: =I23+H23 -> 42621.639 | L23: Action anticipée
C24: Paramétrage package_splitter_cmd.properties | D24: 23 | E24: CGI | F24: Pierre | G24: Terminé | H24: 0.0069444444 | I24: =J23 -> 42621.639 | J24: =I24+H24 -> 42621.646 | L24: Action anticipée
C25: Paramétrage package_splitter_tables.txt | D25: 24 | E25: CGI | F25: Pierre | G25: Terminé | H25: 0.0069444444 | I25: =J24 -> 42621.646 | J25: =I25+H25 -> 42621.653 | L25: Action anticipée
C26: Paramétrage table_splitter_tables.txt | D26: 25 | E26: CGI | F26: Pierre | G26: Terminé | H26: 0.0069444444 | I26: =J25 -> 42621.653 | J26: =I26+H26 -> 42621.66 | L26: Action anticipée
C27: Configuration base Oracle source | D27: 26 | E27: CGI | F27: Pierre | G27: Terminé | H27: 0.0013888889 | I27: =J19+0.01 -> 42622.289 | J27: =I27+H27 -> 42622.291 | L27: Action anticipée
C28: Lancement des opérations d’export | G28: Terminé
C29: Mise en place de distribution monitor | D29: 31 | E29: CGI | F29: Pierre | G29: Terminé | H29: 0 | I29: =J27 -> 42622.291 | J29: =I29+H29 -> 42622.291 | L29: Action anticipée
C30: Prepare | D30: 32 | E30: CGI | F30: Pierre | G30: Terminé | H30: 0.020833333 | I30: =J29 -> 42622.291 | J30: =I30+H30 -> 42622.311
C31: Distribution Monitor Export | D31: 33 | E31: CGI | F31: Pierre | G31: Terminé | H31: 0.091666667 | I31: =J30 -> 42622.311 | J31: =I31+H31 -> 42622.403
C32: Suppression du système Non Unicode | D32: 40 | E32: CGI | F32: Pierre | G32: Terminé | H32: 0.0069444444 | I32: =J30 -> 42622.311 | J32: =I32+H32 -> 42622.318 | L32: Parallélisation avec la phase PREPARE du DM
B33: Import | I33: =J31 -> 42622.403 | J33: =I33+H33 -> 42622.403
C34: Lancement des opérations d’import | D34: 50 | E34: CGI | F34: Pierre | G34: Terminé | I34: =I31 -> 42622.311 | J34: =I34+H34 -> 42622.311 | L34: Parallélisation avec la phase EXPORT du DM
C35: SAPInst : Installation de l'ASCS | D35: 51 | E35: CGI | F35: Pierre | G35: Terminé | H35: 0.0069444444 | I35: =J34 -> 42622.311 | J35: =I35+H35 -> 42622.318
C36: SAPInst : Installation de la BDD et Import | D36: 52 | E36: CGI | F36: Pierre | G36: Terminé | H36: 0.0069444444 | I36: =J35 -> 42622.318 | J36: =I36+H36 -> 42622.325 | L36: Parallélisation avec la phase EXPORT du DM
C37: Installation de la BDD | D37: 53 | E37: CGI | F37: Pierre | G37: Terminé | H37: 0.013888889 | I37: =J36 -> 42622.325 | J37: =I37+H37 -> 42622.339 | L37: Parallélisation avec la phase EXPORT du DM
C38: Configuration Oracle | D38: 54 | E38: CGI | F38: Pierre | G38: Terminé | H38: 0.0034722222 | I38: =J37 -> 42622.339 | J38: =I38+H38 -> 42622.343 | L38: Parallélisation avec la phase EXPORT du DM
C39: Distribution Monitor Import | D39: 55 | E39: CGI | F39: Pierre | G39: Terminé | H39: 0.12847222 | I39: =J38 -> 42622.343 | J39: =I39+H39 -> 42622.471
C40: SAPInst : Installation de la BDD : Fin | D40: 56 | E40: CGI | F40: Pierre | G40: Terminé | H40: 0.0097222222 | I40: =J39 -> 42622.471 | J40: =I40+H40 -> 42622.481
C41: SAPInst : Installation PAS | D41: 57 | E41: CGI | F41: Pierre | G41: Terminé | H41: 0.041666667 | I41: =J40 -> 42622.481 | J41: =I41+H41 -> 42622.522 | L41: Numéro d'instance : 03
C42: SAPInst : Installation ERS | D42: 58 | E42: CGI | F42: Pierre | G42: Terminé | H42: 0 | I42: =J41 -> 42622.522 | J42: =I42+H42 -> 42622.522 | L42: Numéro d'instance ERS pour PPH : 10 A rajouter les fichiers de profiles ERS et SCS: enque/repl/shadow_file_name = /usr/sap/PPH/ERS10/data/SHM_FILESYS_BACKUP
C43: SAPInst : Installation AS sur PAS QVIPBSAPAH02 | D43: 58 | E43: CGI | F43: Pierre | G43: Terminé | I43: =J42 -> 42622.522 | J43: =I43+H43 -> 42622.522 | L43: Numéro d'instance : 01
C44: SAPInst : Installation AS sur QVIPBSAPAH03 | D44: 59 | E44: CGI | F44: Pierre | G44: Terminé | H44: 0.020833333 | I44: =J42 -> 42622.522 | J44: =I44+H44 -> 42622.543 | L44: Numéro d'instance : 00 Veiller à ce que le montage NFS pour /sapmnt/PPH/exe soit paramétré avec l'option no_root_squash Supprimer le contenu du répertoire /usr/sap/PPH/SYS/exe contenant des anciens liens symboliques
C45: SAPInst : Installation AS sur QVIPBSAPAH04 | D45: 60 | E45: CGI | F45: Pierre | G45: Terminé | H45: 0.020833333 | I45: =J42 -> 42622.522 | J45: =I45+H45 -> 42622.543 | L45: Numéro d'instance : 00 Veiller à ce que le montage NFS pour /sapmnt/PPH/exe soit paramétré avec l'option no_root_squash Supprimer le contenu du répertoire /usr/sap/PPH/SYS/exe contenant des anciens liens symboliques
C46: SAPInst : Installation AS sur QVIPBSAPAH05 | D46: 59 | E46: CGI | F46: Pierre | G46: Terminé | H46: 0.020833333 | I46: =J42 -> 42622.522 | J46: =I46+H46 -> 42622.543 | L46: Numéro d'instance : 00 Veiller à ce que le montage NFS pour /sapmnt/PPH/exe soit paramétré avec l'option no_root_squash Supprimer le contenu du répertoire /usr/sap/PPH/SYS/exe contenant des anciens liens symboliques
C47: SAPInst : Installation AS sur QVIPBSAPAH06 | D47: 60 | E47: CGI | F47: Pierre | G47: Terminé | H47: 0.020833333 | I47: =J42 -> 42622.522 | J47: =I47+H47 -> 42622.543 | L47: Numéro d'instance : 00 Veiller à ce que le montage NFS pour /sapmnt/PPH/exe soit paramétré avec l'option no_root_squash Supprimer le contenu du répertoire /usr/sap/PPH/SYS/exe contenant des anciens liens symboliques
C48: SAPInst : Installation AS sur QVIPBSAPAH07 | D48: 59 | E48: CGI | F48: Pierre | G48: Terminé | H48: 0.020833333 | I48: =J42 -> 42622.522 | J48: =I48+H48 -> 42622.543 | L48: Numéro d'instance : 00 Veiller à ce que le montage NFS pour /sapmnt/PPH/exe soit paramétré avec l'option no_root_squash Supprimer le contenu du répertoire /usr/sap/PPH/SYS/exe contenant des anciens liens symboliques
C49: SAPInst : Installation AS sur QVIPBSAPAH08 | D49: 60 | E49: CGI | F49: Pierre | G49: Terminé | H49: 0.020833333 | I49: =J42 -> 42622.522 | J49: =I49+H49 -> 42622.543 | L49: Numéro d'instance : 00 Veiller à ce que le montage NFS pour /sapmnt/PPH/exe soit paramétré avec l'option no_root_squash Supprimer le contenu du répertoire /usr/sap/PPH/SYS/exe contenant des anciens liens symboliques
C50: SAPInst : Installation AS sur QVIPBSAPAH09 | D50: 59 | E50: CGI | F50: Pierre | G50: Terminé | H50: 0.020833333 | I50: =J45 -> 42622.543 | J50: =I50+H50 -> 42622.564 | L50: Numéro d'instance : 00 Veiller à ce que le montage NFS pour /sapmnt/PPH/exe soit paramétré avec l'option no_root_squash Supprimer le contenu du répertoire /usr/sap/PPH/SYS/exe contenant des anciens liens symboliques
C51: SAPInst : Installation AS sur QVIPBSAPAH10 | D51: 60 | E51: CGI | F51: Pierre | G51: Terminé | H51: 0.027777778 | I51: =J45 -> 42622.543 | J51: =I51+H51 -> 42622.571 | L51: Numéro d'instance : 00 Veiller à ce que le montage NFS pour /sapmnt/PPH/exe soit paramétré avec l'option no_root_squash Supprimer le contenu du répertoire /usr/sap/PPH/SYS/exe contenant des anciens liens symboliques
B52: Post opérations | I52: =J41 -> 42622.522 | J52: =I52+H52 -> 42622.522
C53: Post-Upgrade | G53: Terminé
C54: Notifier DI.VB de lancer le back up FULL online | D54: 61 | E54: DI.VB | G54: Terminé | H54: 0.0034722222 | I54: =J47 -> 42622.543 | J54: =I54+H54 -> 42622.547 | L54: 30/08 Lancement de la Full Online
C55: SM28 - Consistency Check | D55: 62 | E55: CGI | F55: Pierre | G55: Terminé | H55: 0.0013888889 | I55: =J54 -> 42622.547 | J55: =I55+H55 -> 42622.548
C56: SMLT - Langues : RSTLAN_AFTER_UPGRADE | D56: 63 | E56: CGI | F56: Pierre | G56: Terminé | H56: 0.0069444444 | I56: =J55 -> 42622.548 | J56: =I56+H56 -> 42622.555
C57: SMLT - Langues : Supplémentation Intermandant | D57: 64 | E57: CGI | F57: Pierre | G57: Terminé | H57: 0.0034722222 | I57: =J56 -> 42622.555 | J57: =I57+H57 -> 42622.559
C58: SMLT - Langues : Supplémentation Mandant Ref | D58: 65 | E58: CGI | F58: Pierre | G58: Terminé | H58: 0.010416667 | I58: =J57 -> 42622.559 | J58: =I58+H58 -> 42622.569
C59: MAJ Profils d'instance | D59: 66 | E59: CGI | F59: Pierre | G59: Terminé | H59: 0.03125 | I59: =J58 -> 42622.569 | J59: =I59+H59 -> 42622.6 | L59: Phase à optimiser en production, possible de réaliser les calculs avant l'upgrade avec sappfar
C60: Vidage des tables MONI etc | D60: 67 | E60: CGI | F60: Pierre | G60: Terminé | H60: 0.0034722222 | I60: =J59 -> 42622.6 | J60: =I60+H60 -> 42622.604
C61: Restauration des logs de jobs | D61: 68 | E61: CGI | F61: Pierre | G61: Terminé | H61: 0.0034722222 | I61: =J60 -> 42622.604 | J61: =I61+H61 -> 42622.607
C62: RZ04 : Mode exploitation | D62: 69 | E62: CGI | F62: Pierre | G62: Terminé | H62: 0.010416667 | I62: =J61 -> 42622.607 | J62: =I62+H62 -> 42622.618
C63: /ASU/UPGRADE | D63: 70 | E63: CGI | F63: Pierre | G63: Terminé | H63: 0.0034722222 | I63: =J62 -> 42622.618 | J63: =I63+H63 -> 42622.621
C64: Finalisation de la conversion Unicode | F64: Pierre
C65: Gestion des tables TLOCK* | D65: 81 | E65: CGI | F65: Pierre | G65: Terminé | H65: 0.0034722222 | I65: =J63 -> 42622.621 | J65: =I65+H65 -> 42622.625
C66: MAJ RFC | D66: 82 | E66: CGI | F66: Pierre | G66: Terminé | H66: 0.0034722222 | I66: =J65 -> 42622.625 | J66: =I66+H66 -> 42622.628
C67: Mise au standard AirFrance | F67: Pierre
C68: Statistiques Oracle | D68: 93 | E68: CGI | F68: Pierre | G68: Terminé | H68: 0.017361111 | I68: =J66 -> 42622.628 | J68: =I68+H68 -> 42622.645
C69: Ouvrir l’accès gateway | D69: 96 | E69: CGI | F69: Pierre | G69: Terminé | H69: 0.0034722222 | I69: =J68 -> 42622.645 | J69: =I69+H69 -> 42622.649
C70: Déverouiller les Jobs standards | D70: 97 | E70: CGI | F70: Pierre | G70: Terminé | H70: 0.0034722222 | I70: =J69 -> 42622.649 | J70: =I70+H70 -> 42622.652
C71: Mise à jour des paramètres Oracles | D71: 98 | E71: CGI | F71: Pierre | G71: Terminé | H71: 0.017361111 | I71: =J70 -> 42622.652 | J71: =I71+H71 -> 42622.67
C72: Importer les Ots OPENHR | D72: 99 | E72: CGI | F72: Pierre | G72: Terminé | H72: 0.0034722222 | I72: =J71 -> 42622.67 | J72: =I72+H72 -> 42622.673 | L72: Il faut supprimer complètement la STMS et la recréer en l'intégrant dans le controleur de domaine DVH - utiliser l'ancien mot de passe de TMSADM A importer l'un après l'autre -DVMK900236 - P-UPECCHR-FD905513-Recuperation Objets OpenHR-02 (code 8 attendu) -DVMK900241 - P-UPECCHR-FD905513-Recuperation Objets OpenHR-03
C73: Lancer le RTCCTOOL | D73: 100 | E73: CGI | F73: David | G73: Terminé | H73: 0.03125 | I73: =J72 -> 42622.673 | J73: =I73+H73 -> 42622.704 | L73: - Import du package SAPK-74003INSTPI - Penser à installer une licence de maintenance sur les systèmes - La SPAM se termine lorsque le declustering se terminé.
C74: Declustering | D74: 101 | E74: CGI | F74: David | G74: Terminé | H74: 0.64652778 | I74: 42622.854 | J74: =I74+H74 -> 42623.501 | L74: Import de l'OT DVHK960029 - contenant les actions faîtes sur DVH. Augmenter à 120 GO sur PSAPUNDO et au moins 30 GO pour PSAPTEMP sinon interruption de l'opération durant la nuit Le depooling sur la table CDPOS dure plus de 10 heures lors du DR2. Action relancée à 20h30
C75: Redimensionner PSAPTEMP et PSAPUNDO | D75: 102 | E75: CGI | F75: David | G75: Terminé | H75: 0.020833333 | I75: =J74 -> 42623.501 | J75: =I75+H75 -> 42623.522 | L75: PSAPTEMP : 8 Go dans /oracle/PPH/sapdata0 PSAPUNDO : 13 Go dans /oracle/PPH/sapdata1
C76: Passage en autoextend off sur les datafiles | D76: 91 | E76: CGI | F76: David | G76: Terminé | H76: 0.024305556 | I76: =J75 -> 42623.522 | J76: =I76+H76 -> 42623.546
C77: Supprimer ou déplacer le répertoire /usr/sap/trans/upgrade en fin d'upgrade | D77: 104 | E77: CGI | F77: Pierre | G77: Terminé | H77: 0.0013888889 | I77: =J76 -> 42623.546 | J77: =I77+H77 -> 42623.547 | L77: Sauvegardé dans /BackupSUM/SUM_PPH/upgrade_DR2
C78: Supprimer le lien symbolique /usr/sap/trans/EPS/in pour les SP | D78: 105 | E78: CGI | F78: Pierre | G78: Terminé | H78: 0.0013888889 | I78: =J77 -> 42623.547 | J78: =I78+H78 -> 42623.549 | L78: Etape rajoutée
C79: Faire la SGEN | D79: 105 | E79: CGI | F79: Pierre | G79: Terminé | H79: 0 | I79: =J78 -> 42623.549 | J79: =I79+H79 -> 42623.549 | L79: Anticipée
A80: Post-Upgrade
B81: Vérifications techniques post upgrade
C82: Cf Onglet 4

Sheet 04 - Post Upgrade
C1: ACTIVITY | D1: TASK ID | E1: Resp. dept. | F1: ACTOR | G1: Status | H1: Duration | I1: Planned Start | J1: Planned End | K1: Dependency | L1: Comments
A2: Export - Import - Détail dans onglet 03 - Export - Import
B3: Post opérations
A6: Post-Upgrade
B7: Post upgrade FrontEnd | I7: =J60 -> 42624.224 | J7: =I7+H7 -> 42624.224
A8: X | C8: Connexion UME en mode Load Balancing sur le nouveau PRH | E8: DI.VB | F8: Gregory | G8: Terminé | H8: 0.0069444444 | I8: 42623.875 | J8: =I8+H8 -> 42623.882
C9: Mise en exploitation du nouveau portail sur le CCMS | E9: DI.VB | F9: Gregory | G9: En cours | H9: 0.0069444444 | I9: =J8 -> 42623.882 | J9: =I9+H9 -> 42623.889
C10: conf HP OVO sur le portail eRH | E10: DI.VB | F10: Gregory | G10: En cours | H10: 0.0069444444 | I10: =J9 -> 42623.889 | J10: =I10+H10 -> 42623.896
C11: Configuration SSO entre le backend et le frontend | E11: DI.VB | F11: Gregory | G11: Terminé | H11: 0.0069444444 | I11: =J9 -> 42623.889 | J11: =I11+H11 -> 42623.896
C12: Validation des destinations JCO WD_MODELDATA_XSS & WD_RFC_METADATA_XSS | E12: DI.VB | F12: Gregory | G12: Terminé | H12: 0.0034722222 | I12: =J11 -> 42623.896 | J12: =I12+H12 -> 42623.899
C13: Validation de la RFC "SAP_R3_HRJcoConnection" | E13: DI.VB | F13: Gregory | G13: Terminé | H13: 0.0034722222 | I13: =J12 -> 42623.899 | J13: =I13+H13 -> 42623.903
C14: Création de la RFC "SAP_R3_HumanResources$WebFlowConnector" | E14: DI.VB | F14: Gregory | G14: Terminé | H14: 0.0034722222 | I14: =J13 -> 42623.903 | J14: =I14+H14 -> 42623.906
C15: Installation et configuration Loginmodule CA Siteminder SSO for SAP Web AS | E15: DI.VB | F15: Gregory | G15: Reporté | H15: 0.0034722222 | I15: =J14 -> 42623.906 | J15: =I15+H15 -> 42623.91
C16: Installation/configuration/vérification ADS | E16: DI.VB | F16: Gregory | G16: Terminé | H16: 0.0034722222 | I16: =J15 -> 42623.91 | J16: =I16+H16 -> 42623.913
C17: Vérification paramètre instance J2EE sap.max.session.limit à -1 | E17: DI.VB | F17: Gregory | G17: Terminé | H17: 0.0034722222 | I17: =J16 -> 42623.913 | J17: =I17+H17 -> 42623.917
C18: Check paramètre login SSO ume.logon_force_password_change_on_sso | E18: DI.VB | F18: Gregory | G18: Terminé | H18: 0.0034722222 | I18: =J17 -> 42623.917 | J18: =I18+H18 -> 42623.92
C19: Check version JAR UWL | E19: DI.VB | F19: Gregory | G19: Terminé | H19: 0.0034722222 | I19: =J18 -> 42623.92 | J19: =I19+H19 -> 42623.924
C20: Habile : Valorisation de la page de déconnexion (paramétrage ) | E20: DI.VB | F20: Gregory | G20: Terminé | H20: 0.0034722222 | I20: =J19 -> 42623.924 | J20: =I20+H20 -> 42623.927
C21: Vérification page par défaut du Portail (/irj/portal) | E21: DI.VB | F21: Gregory | G21: Terminé | H21: 0.0034722222 | I21: =J20 -> 42623.927 | J21: =I21+H21 -> 42623.931
C22: Arret/redémarrage du portail PW1 | E22: DI.VB | F22: Gregory | G22: Terminé | H22: 0.03125 | I22: =J21 -> 42623.931 | J22: =I22+H22 -> 42623.962
B23: Post upgrade BackEnd | I23: =J76 -> 42624.264 | J23: =I23+H23 -> 42624.264
A24: 0 | C24: Migration configuration Cluster | E24: DI.VB / DI.SY | F24: PA | G24: Terminé | H24: 0 | I24: ='03 - Export - Import'!J74-0.05 -> 42623.451 | J24: =I24+H24 -> 42623.451 | L24: 30/08 PA : ne concerne que PRH - Parallélisation avec la phase de déclustering
C25: Tests de bascule | E25: DI.VB / DI.SY | F25: PA | G25: Terminé | H25: 0 | I25: ='03 - Export - Import'!J79 -> 42623.549 | J25: =I25+H25 -> 42623.549 | L25: 30/08 PA : ne concerne que PRH - redémarrages ==> Faisable par GREG?
C26: Check DIVB.SA | E26: DI.VB | F26: PA | G26: Terminé | H26: 0.041666667 | I26: ='03 - Export - Import'!J74 -> 42623.501 | J26: =I26+H26 -> 42623.542 | L26: 30/08 PA : Parallélisation avec la phase de déclustering
C27: Check DIVB.SA non parralélisable avec le déclustering | E27: DI.VB | F27: PA SP | G27: Terminé | H27: 0.03125 | I27: ='03 - Export - Import'!J74 -> 42623.501 | J27: =I27+H27 -> 42623.532 | L27: 30/08 PA==> Faisable par GREG?
C28: Valorisation paramètre mémoire ABAP | E28: DI.VB | F28: PA SP | G28: Terminé | I28: =J27 -> 42623.532 | J28: =I28+H28 -> 42623.532 | L28: Vérifier le paramétagre machine (les AS de PRH) : ==> Faisable par GREG? abap/heap_area_nondia = 6442450944 abap/heap_area_total = 12884901888 rdisp/PG_MAXFS = 262144 rdisp/PG_SHM = 32768
C29: Vérification des ordres passés (OT SPDD et Hercule) | D29: 1 | E29: CGI | F29: Emmanuel | G29: Terminé | H29: 0.013888889 | I29: 42623.583 | J29: =I29+H29 -> 42623.597 | L29: OT SPDD : DVHK960007, DVHK960090 et DVHK960018 (pas de journal des transports mais si les 2 autres sont passés, c'est OK) et DVHK960015. ==> REX sur cet OT, retransporté le 25/08. OT HERCULE : A passer obligatoirement A importer un par un : -DVHK955110 -DVHK960027 -DVHK955110 -DVHK955108 + OTs de données dépendants du système et à refaire à chaque fois. Les 4 Ots de sauvegarde des données Hercule : (non valide pour le DR1 PPHK900011 , PPHK900012 , PPHK900013 , PRHK900135) OTs de Julien importés dans le DR2 PRHK900142 PRHK900141 PRHK900140 PRHK900139 3 Ots sauvegarde des données HERCULE pour FRH : FRHK900047 , FRHK900048 , FRHK900049
C30: Vérifier l'existence des groupes de fonction ZFOR_WORKFLOWS et ZGRH_CCNTA ( Deux entrées manquantes en TLIBG) | D30: 2 | E30: CGI | F30: Emmanuel | G30: Terminé | H30: 0.0034722222 | I30: =J29 -> 42623.597 | J30: =I30+H30 -> 42623.601 | L30: Faire se16 sur la table TLIBG Puis vérifier en SE80, groupe de fonction … Si absent, passer le : DVHK960090 4119573 P-UPECCHR-MOVE4HR-Module fonction manquant sur QSH-01
C31: Vérifier les Objets Open HR Manquant | D31: 3 | E31: CGI | F31: Emmanuel | G31: Terminé | H31: 0.0034722222 | I31: =J30 -> 42623.601 | J31: =I31+H31 -> 42623.604 | L31: Vérifier le transports des Ots : DVMK900236 - P-UPECCHR-FD905513-Recuperation Objets OpenHR-02 (code 8 atendu) DVMK900241 - P-UPECCHR-FD905513-Recuperation Objets OpenHR-03
C32: Données Infotype 9*** manquantes Lancer le programme RPUMS40CCI | D32: 4 | E32: CGI | F32: Emmanuel | G32: Terminé | H32: 0.0069444444 | I32: =J31 -> 42623.604 | J32: =I32+H32 -> 42623.611 | L32: Lancer le programme RPUMS40CCI pour recréer les includes %_HR9**** Infotypes = 9* Générer include infotype = Coché Générer strucutres données supp = Coché Gérer uniquement T77ID = Décoché Mode test = X lors du premier lancement, vérifier pas d'erreur décoché pour le vrai lancement Suite FRH et DR2, il est nécessaire de lancer deux fois cette étape. Vérifier également la présence du 9507.
C33: Vérification des infotypes | E33: CGI | F33: Emmanuel | G33: Terminé | H33: 0.0034722222 | I33: =J32 -> 42623.611 | J33: =I33+H33 -> 42623.615 | L33: Lancer en SE38, il faut que les programmes %_HR9* doivent exister 9* = 9008, 9500, 9501, 9502, 9503, 9504, 9506, 9508, 9509, 9510, 9512, 9522,9523, 9524, 9529, 9801, 9802, 9803, 9871, 9872, 9884, 9891, 9892, 9893, 9894
C34: SPAU + 1° report de maintenance | D34: 5 | E34: CGI / DI.VB | F34: Emmanuel | G34: Terminé | H34: 0.024305556 | I34: =J33 -> 42623.615 | J34: =I34+H34 -> 42623.639 | L34: Liste d'Ots à transporter Liste 1 ==> Qui coté VB passe les OT? OK par GREG?
C35: Mise à jour des IBAN | D35: 6 | E35: CGI | F35: Emmanuel | G35: Terminé | H35: 0.010416667 | I35: =J34 -> 42623.639 | J35: =I35+H35 -> 42623.649 | L35: Attention, lancement en deux étapes : 1 - Sur le user de PAVEL : - SE16 table PA0009, PERNR = 41277742 et lancer. Vérifier que la colonne ZZIBAN renseignée sur au moins 1 ligne (juillet 2011 dans la table). Le but du programme est de copier le contenu de la zone ZZIBAN dans la zone IBAN. - Premier lancement sur le user 41277742. uniquement avec le numéro de matricule. (autres zones à vide). - Si IBAN alimentée, relancer sur toute la population. 2 - sur toute la population Lancement du programme ZHR_MAJ_IT0009 et vérifier sur tous les matricules S_PERNR =Vide S_BEGDA = Vide S_ENDDA = Vide Vérifier la table - Volumétrique (nb de ZZiban alimenté = nb Iban alimenté) - ZZIBAN = vide et IBAN <> vide (doit être 0) - ZZIBAN <> vide et IBAN = vide (doit être 0) - Qualitatif : sur les 200 première entrées alimentées.
C36: Mise à jout du cluster TE - transport OT | D36: 7 | E36: CGI / DI.VB | F36: Emmanuel | G36: Terminé | H36: 0.0034722222 | I36: =J35 -> 42623.649 | J36: =I36+H36 -> 42623.653 | L36: Liste d'Ots à transporter Liste 2
C37: Mise à jout du cluster TE - Maj + vérif | D37: 8 | E37: CGI | F37: Emmanuel | G37: Terminé | H37: 0.013888889 | I37: =J36 -> 42623.653 | J37: =I37+H37 -> 42623.667 | L37: 2 étapes : 1 - Vérification via la transaction ZPRTE Mettre le matricule de Pavel / F8 ==> On obtient la liste de tous les déplacements. SI on double clic sur une ligne (zone déplacement), on a un dump. 2 -Lancement de ZTV_MAJ_CLUSTER_TE sur le user de test Matricule = Celui de test N° déplacement = Vide Première màj = Coché Mise à jour BELEG par fichier = Vide Nom du fichier = Vide. 2 - Contolre(faire le contrôle avec ZPRTE) Avec le matricule de tests, afficher le contenu de la table BELEG (sléctionner BELEG) et petites lunettes (on peut également controler les autres zones qui ne sont pas à vide). Vérifier que le contenu est cohérent en terme de format (Origine = B, E, M). L'erreur pourrait venir d'un décalage de zone. 4 - Lancer le programme sur le reste de la population. Attentioin, il ne faut pas relancer sur le user de test. Matricule = Différent du matricule de test. Attention, break point sur le matricule d'Emmanuel. 5 - Faire un controle sur une 10 de matricules. Pour inofmration, le jeu de test peut être récupérer dans la table PTRV_PERIO.
C38: Transport OTs Autorisation + Second report de maintenance + Defects | D38: 10 | E38: CGI / DI.VB | F38: Emmanuel | G38: Terminé | H38: 0.03125 | I38: =J37 -> 42623.667 | J38: =I38+H38 -> 42623.698 | L38: Liste d'Ots à transporter Liste 3 Attention le transport du DVHK960125 est très long - Prévoir à transporter en arrière-plan. Voir à supprimer les logs plus tard
C39: Vérifier une traduction | D39: 11 | E39: CGI | F39: Emmanuel | G39: Terminé | H39: 0.0034722222 | I39: =J38 -> 42623.698 | J39: =I39+H39 -> 42623.701 | L39: CF defect 23 Pour vérifier que les traductions sont à faire, ZHORAIRES / Gestion des horaires PRP, RPR / 01 / Non / Vérifier que la zone NB RTT Hebdo en Zone 14 et que HrRmCY dans la 15. Si KO : Aller en SE11, voir les traductions pour les éléments de données M2STD et JRSTD. Faut valider les traduction… Mettre Langue source DE Langue cible FR Mettre à jour avec ce qu'il y a en DVH 200 ou QSH
C40: Transport Ots | D40: 12 | E40: CGI / DI.VB | F40: Emmanuel | G40: Terminé | H40: 0.0034722222 | I40: =J39 -> 42623.701 | J40: =I40+H40 -> 42623.705 | L40: Liste d'Ots à transporter Liste 4
C41: Transport Ots | D41: 13 | E41: CGI / DI.VB | F41: Emmanuel | G41: Terminé | H41: 0.0034722222 | I41: =J40 -> 42623.705 | J41: =I41+H41 -> 42623.708 | L41: Liste d'Ots à transporter Liste 5
C42: Transport Ots | D42: 14 | E42: CGI / DI.VB | F42: Emmanuel | G42: Terminé | H42: 0.0034722222 | I42: =J41 -> 42623.708 | J42: =I42+H42 -> 42623.712 | L42: Liste d'Ots à transporter Liste 6
C43: Transport Ots | D43: 15 | E43: CGI / DI.VB | F43: Emmanuel | G43: Terminé | H43: 0.0034722222 | I43: =J42 -> 42623.712 | J43: =I43+H43 -> 42623.715 | L43: Liste d'Ots à transporter Liste 7
C44: Transport Ots | D44: 16 | E44: CGI / DI.VB | F44: Emmanuel | G44: Terminé | H44: 0.0034722222 | I44: =J43 -> 42623.715 | J44: =I44+H44 -> 42623.719 | L44: Liste d'Ots à transporter Liste 8
C45: Transport Ots | D45: 17 | E45: CGI / DI.VB | F45: Emmanuel | G45: Terminé | H45: 0.010416667 | I45: =J44 -> 42623.719 | J45: =I45+H45 -> 42623.729 | L45: Liste d'Ots à transporter Listes 9 et 10 Attention à bien prendre en compte également les Ots de Julien TWS (2 Ots TV1K*) + Informatica (13 OT DVHK*)
C46: Transport OT DSM | D46: 18 | E46: CCSAP / DI.VB | F46: DI.VB.SA | G46: Terminé | H46: 0.017361111 | I46: =J45 -> 42623.729 | J46: =I46+H46 -> 42623.747 | L46: Demande DI.VB.SA, import E8BK900024 : DSM4 for ERP build 95 avec option "Import Transport Request Again, Overwrite Originals, Overwrite Objects in Unconfirmed Repairs et Ignore Invalid Component Version" (temps masqué)
C47: Import des templates Excel dans le mandant 000 | D47: 19 | E47: DI.VB | F47: DI.VB.SA | G47: Terminé | I47: =J45 -> 42623.729 | J47: =I47+H47 -> 42623.729 | L47: Step 4 de la note 1937247 (action DI.VB.SA sur mandant 000). Cf DMI 544731
D48: 20 | E48: CGI | F48: Emmanuel | G48: Terminé | H48: 0.0034722222 | I48: =J47 -> 42623.729 | J48: =I48+H48 -> 42623.733 | L48: + CF Defect 501 - voir mode opératoire d'Anne Saintpierre pour la traduction de WWEEK
C49: Process TTA | D49: 21 | E49: CGI | F49: Emmanuel | G49: Terminé | H49: 0.0034722222 | I49: =J48 -> 42623.733 | J49: =I49+H49 -> 42623.736 | L49: Lancer la SE16 sur la table ZTPCPNC_TTA_DESI afin de générer le programme /1BCDWB/DBZTPCPNC_TTA_DESI. Lancer la SE16 sur la table ZTPCPNC_MOB_DESI afin de générer le programme /1BCDWB/DBZTPCPNC_MOB_DESI. (CF Defect 442) Tester la transaction ZC_TTA_GESTCAMP, option Afficher l'historique des desiderata. Tester la transaction ZC_MOB_GESTCAMP, afficher l'historique des demandes de mobilité
C50: Création variable Z_UPGRADE_ECC6 | D50: 22 | E50: CGI | F50: Emmanuel | G50: Terminé | H50: 0.00069444444 | I50: =J49 -> 42623.736 | J50: =I50+H50 -> 42623.737 | L50: Transaction STVARV, se mettre en mode modification et créer un nouvelle entrée. Nom : Z_UPGRADE_ECC6 Valeur : date de la fermeture aux users de PRH au format aaaammjj
C51: Option spool en arrière plan | D51: 23 | E51: CGI | F51: Emmanuel | G51: Terminé | H51: 0.0034722222 | I51: =J50 -> 42623.737 | J51: =I51+H51 -> 42623.74 | L51: Paramétrage des options d'impression. programme RSPRIPARADMIN. Nom = ALVST (statistiques ALV) Cliquer sur "Reprendre valeurs par défaut" ==> Deux lignes doivent s'ajouter Dial = Non Arr.-plan = Non. Sauvegarder. Obectif : Supprimer la page de garde des spool contenant les statistiques ALV, cf defect 243.
C52: Adaptation de l'interface ZHRA | D52: 24 | E52: CGI | F52: Emmanuel | G52: Terminé | H52: 0.010416667 | I52: =J51 -> 42623.74 | J52: =I52+H52 -> 42623.751 | L52: Vérifier les entrées de T532A et vérifier après un premier traitement la T532L pour le code interface ZHRA il faut regénérer l'interface ZHRA par la transaction PU12. SE16 T532A, FLDID = ZHRA, TABNA = P0001 Vérifier qu'il existe les zones SGMNT en positions 51 et BUDGET_PD en positions 52. SE16 T532L, FLDID = ZHRA, DICNA = P0001 Vérifier qu'il existe les zones SGMNT en positions 51 et BUDGET_PD en positions 52 sur la version 02. PU12 / configuration / Format interface = ZHRA / Cliquer sur Générer. Demande 1 OT dont on ne fera rien. libellé = NE PAS TRANSPORTER. ==> Voir avec Pavel car il faut tester un flux de l'interface HRA (rubrique). En attente retour de Pavel sur le test unitaires de l'interface
C53: Mise à jour des tables ZTTV_Log_Matis et ZTTV_Histo_Matis année 2016 | D53: 25 | E53: CGI | F53: Emmanuel | G53: Terminé | H53: 0.125 | I53: =J52 -> 42623.751 | J53: =I53+H53 -> 42623.876 | L53: Lancer le programme ZTV_UPDATE_HISTO_LOG Mode sélection matricule = Coché Mode "mise à jour" = Vide N° Déplacement = vide Matricule = Liste communiquée par Emmanuel (onglet tranches de ce fichier, colonnes K et L) S_DATE = 2016 puis Tout ce qui est avant 1/1/2016 Type de données historiques = Laisser les valeurs par défaut (F, Y, H, T, V) Tables des historiques = Cochée Tables des logs = Cochée NB sec entre chaque traitement = 50 Mode Test = Vide Lancer en arrière plan attendre que le job soit terminé pour lancer sur la tranche suivante. Commencer par traiter 2016 lors des opérations post upgrade. Faire ensuite les autres années. Pour vérifer les données à traiter : ZTTV_Log_Matis ou ZTTV_Histo_MAtis. Il faut lancer le programme pour les deux tables.
B54: Vérifications techniques post upgrade
C55: Vérif présence /transfertinformatica FS + taille | E55: CC SAP | F55: JBE | G55: Terminé | H55: 0.0034722222 | I55: 42624.208 | J55: =I55+H55 -> 42624.212
C56: Vérif user : infa + password | E56: CC SAP | F56: JBE | G56: Terminé | H56: 0.0034722222 | I56: =J55 -> 42624.212 | J56: =I56+H56 -> 42624.215
C57: Vérif SAP : SAPPC + password | E57: CC SAP | F57: JBE | G57: Terminé | H57: 0.0034722222 | I57: =J56 -> 42624.215 | J57: =I57+H57 -> 42624.219
C58: INFORMATICA - Passage à la 9.6.1 + nouveaux extracteurs | E58: CCSAP | F58: JBE | G58: Terminé | H58: 0.0034722222 | I58: =J57 -> 42624.219 | J58: =I58+H58 -> 42624.222 | L58: Liste des Ots en attende de validation par Sébastien HUALME, Jean-Jacques MOLE
C59: DSM : Demande Installation de DSM 4.0 Build 95 | E59: CCSAP | F59: JBE | G59: Terminé | H59: 0 | I59: =J58 -> 42624.222 | J59: =I59+H59 -> 42624.222 | L59: Demande DI.VB.SA, import E8BK900024 : DSM4 for ERP build 95 avec option "Import Transport Request Again, Overwrite Originals, Overwrite Objects in Unconfirmed Repairs et Ignore Invalid Component Version" (temps masqué avec demande import OT informatica)
C60: Vérifier paramétrage mémoire de la machine | D60: 22 | E60: CCERP | F60: Julien | G60: Terminé | H60: 0.0013888889 | I60: =J59 -> 42624.222 | J60: =I60+H60 -> 42624.224 | L60: PBED 11/08 : suite à opération sur FRH, retour de Julien sur les volumétries à controler : laisser par défaut les abap/heap_area_nondia (2000000000) et abap/heap_area_total (4000000000) et valoriser spécifiquement : rdisp/PG_MAXFS = 131072 rdisp/PG_SHM = 32768 Vérifier le paramétagre machine (PRH) : abap/heap_area_nondia = 6442450944 abap/heap_area_total = 12884901888 rdisp/PG_MAXFS = 262144 rdisp/PG_SHM = 32768
C61: Vérification/activation des services ICF requis pour les BSP + acti SOA Manager + activation HCM_LEARNING | E61: CCSAP | F61: JBE | G61: Terminé | H61: 0.0020833333 | I61: =J60 -> 42624.224 | J61: =I61+H61 -> 42624.226
C62: Anonymisation Service BSP Pratis | E62: CCSAP | F62: JBE | G62: Terminé | H62: 0.0020833333 | I62: =J61 -> 42624.226 | J62: =I62+H62 -> 42624.228
C63: SBT - Check appel SBT, mise à jour du SOAREPO à affiner | E63: CC SAP | F63: JBE / GKE ? | G63: Terminé | I63: =J62 -> 42624.228 | J63: =I63+H63 -> 42624.228 | L63: TPE 31/08: Valider avec Genevieve si contrôles inclus dans tests DINR
C64: Web services à adapter | D64: 18 | E64: CC SAP | G64: Non commencé | I64: =J63 -> 42624.228 | J64: =I64+H64 -> 42624.228 | L64: TPE 31/08:
C65: Configuration Ports Logiques Webservices MATIS SOAMANAGER suivre doc Cao | E65: CCSAP | F65: JBE | G65: Terminé | H65: 0.010416667 | I65: =J64 -> 42624.228 | J65: =I65+H65 -> 42624.238 | L65: Après transport SAP Paramétrer les Web services Travel via soamanager (voir mode op fourni par Cao) ==> Attendre le passage des Ots du Lot 6 pour faire la demande au CCERP.
C66: SAP Portail - Vérification/ajustement du system backend | E66: CC SAP | F66: JBE | G66: Non commencé | I66: =J65 -> 42624.238 | J66: =I66+H66 -> 42624.238 | L66: TPE 31/08: supp. (doublons)
C67: SAP Portail - Vérification/ajustement des JCO à destination du backend | E67: CC SAP / DI.VB | G67: Non commencé | I67: =J66 -> 42624.238 | J67: =I67+H67 -> 42624.238
C68: SAP Portail - Reparamétrage de la communication avec le systeme backend | E68: CC SAP | F68: JBE | G68: Terminé | H68: 0.010416667 | I68: =J67 -> 42624.238 | J68: =I68+H68 -> 42624.249
C69: SAP - Check/modif HTTPURLLOC, RSPOR_T_PORTAL | E69: CC SAP | F69: JBE | G69: Terminé | H69: 0.0020833333 | I69: =J68 -> 42624.249 | J69: =I69+H69 -> 42624.251
C70: RFC - LSO_LEARNING, check RFC SAP_LSO_BACKEND | E70: CC SAP | F70: JBE | G70: Terminé | H70: 0.0020833333 | I70: =J69 -> 42624.251 | J70: =I70+H70 -> 42624.253
C71: SAP - Vérif du service SMTP, revaloriser le user "MAIL_SERVER" puis réactiver | E71: CC SAP | F71: JBE | G71: Terminé | H71: 0.0020833333 | I71: =J70 -> 42624.253 | J71: =I71+H71 -> 42624.255
C72: Vérifier l'envoie de MAIL | G72: Terminé | H72: 0.0020833333 | I72: =J71 -> 42624.255 | J72: =I72+H72 -> 42624.257
C73: Désactiver envoie de MAIL | G73: Terminé | H73: 0.0013888889 | I73: =J72 -> 42624.257 | J73: =I73+H73 -> 42624.258
C74: SAP - Vérif du service SMTP | E74: CC SAP | F74: JBE | G74: Non commencé | I74: =J73 -> 42624.258 | J74: =I74+H74 -> 42624.258
C75: Adaptation RFC (Echange avec coporate), UNICODE | E75: CCSAP | F75: JBE | G75: Terminé | H75: 0.0020833333 | I75: =J74 -> 42624.258 | J75: =I75+H75 -> 42624.26
C76: Permettre l'export de fichier sous format XLS | E76: CC SAP | F76: JBE | G76: Terminé | H76: 0.0034722222 | I76: =J75 -> 42624.26 | J76: =I76+H76 -> 42624.264 | L76: - Vérifier l'affichage "Excel intégré" de la transaction ZLIST_RRH (action CCSAP ?). - Si erreur, checker la présence des templates Excel via le report BCALV_BDS_MAINTENANCE (cf. note 1771260) (action CCSAP ?) - Si templates présent les supprimer report BCALV_BDS_MAINTENANCE (cf. note 1937247) et revérifier la ZLIST_RRH (action CCSAP ?) - Si templates absent ou que le check précédent est KO -> Step 4 de la note 1937247 (action DI.VB.SA sur mandant 000). => voir FDS918666
C77: Vérification INFORMATICA 9.6.1 | E77: CCSAP | F77: JBE | G77: Non commencé | H77: 0.0069444444 | I77: =J76 -> 42624.264 | J77: =I77+H77 -> 42624.271
B78: Post-processing frontend
C79: Appeler le support pour désactivation page maintenance | G79: Terminé | H79: 0.0034722222 | I79: =J77 -> 42624.271 | J79: =I79+H79 -> 42624.274
C80: Désactivation page de maintenance | E80: support | G80: Terminé | H80: 0.0069444444 | I80: =J79 -> 42624.274 | J80: =I80+H80 -> 42624.281 | L80: KHAZ 24/08 : Sur Go du projet
C81: Permettre la connexion directe à un serveur NODE | E81: CCSAP | G81: Terminé | H81: 0.0034722222 | I81: =J80 -> 42624.281 | J81: =I81+H81 -> 42624.285
C82: Validation du nouveau loginmodule HeaderVariableLoginModule | E82: CCSAP | G82: Terminé | H82: 0.0034722222 | I82: =J81 -> 42624.285 | J82: =I82+H82 -> 42624.288 | L82: Déplacement de la tache
C83: Configuration Loginmodule CA Siteminder SSO for SAP Web AS | E83: CCSAP | G83: N/A | H83: 0.0034722222 | I83: =J82 -> 42624.288 | J83: =I83+H83 -> 42624.292 | L83: Déplacement de la tache
C84: configuration/vérification ADS | E84: CCSAP | G84: Terminé | H84: 0.0034722222 | I84: =J83 -> 42624.292 | J84: =I84+H84 -> 42624.295 | L84: Déplacement de la tache
C85: Check droit portail sur PCD (everyone en read à la racine) | E85: CCSAP | F85: JBE | G85: Terminé | H85: 0.00069444444 | I85: =J84 -> 42624.295 | J85: =I85+H85 -> 42624.296 | L85: Déplacement de la tache
C86: Import des epa (Portal Content) | E86: CCSAP | F86: JBE | G86: Terminé | H86: 0.00069444444 | I86: =J85 -> 42624.296 | J86: =I86+H86 -> 42624.297 | L86: Déplacement de la tache
C87: Configuration UWL | E87: CCSAP | F87: JBE | G87: Terminé | H87: 0.0034722222 | I87: =J86 -> 42624.297 | J87: =I87+H87 -> 42624.3 | L87: Déplacement de la tache
C88: Import des fichiers de config xml la worklist | E88: CCSAP | F88: JBE | G88: Terminé | H88: 0.0034722222 | I88: =J87 -> 42624.3 | J88: =I88+H88 -> 42624.303 | L88: Déplacement de la tache
C89: Création Système Backend PRATIS (type HTTP) pour alias URL_PRATIS | E89: CCSAP | F89: JBE | G89: Terminé | H89: 0.0013888889 | I89: =J88 -> 42624.303 | J89: =I89+H89 -> 42624.305 | L89: Déplacement de la tache
C90: Valorisation des règles d'affichage du portail (Theme AF / Theme standard pour user emergency) | E90: CCSAP | F90: JBE | G90: Terminé | H90: 0.0013888889 | I90: =J89 -> 42624.305 | J90: =I90+H90 -> 42624.306 | L90: Déplacement de la tache
C91: Vérif: Mapping Rôle Portail / Rôle Backend | E91: CCSAP | F91: JBE | G91: Terminé | H91: 0.0069444444 | I91: =J90 -> 42624.306 | J91: =I91+H91 -> 42624.313 | L91: Mapping Rôle Portail / Rôle Backend RC:ESS_SALARIE_PPL Mapping Manager Transverse avec les 6 RC*MSS* (pour délégation UWL)
C92: Application note 1753749 - Cannot clear ICM server cache | E92: DI.VB | G92: Non commencé | I92: =J91 -> 42624.313 | J92: =I92+H92 -> 42624.313 | L92: Déplacement de la tache
C93: Application note 1753749 - Cannot clear ICM server cache | E93: DI.VB | G93: En cours | I93: =J92 -> 42624.313 | J93: =I93+H93 -> 42624.313 | L93: 30/08 PA : toujours d'actualité ?
C94: Vérif Chargement des pictos | E94: CCSAP | F94: JBE | G94: Terminé | H94: 0.00069444444 | I94: =J93 -> 42624.313 | J94: =I94+H94 -> 42624.314 | L94: Déplacement de la tache
C95: Habile : Valorisation de la page de déconnexion (vérif) | E95: CCSAP | G95: Terminé | H95: 0.00069444444 | I95: =J94 -> 42624.314 | J95: =I95+H95 -> 42624.315 | L95: Déplacement de la tache
C96: Vérif Import KM pour FAQ | E96: CCSAP | F96: JBE | G96: Terminé | H96: 0.0020833333 | I96: =J95 -> 42624.315 | J96: =I96+H96 -> 42624.317 | L96: Déplacement de la tache
E97: CCSAP | F97: JBE | G97: Non commencé | I97: =J96 -> 42624.317 | J97: =I97+H97 -> 42624.317 | L97: Déplacement de la tache
C98: Transport EPAs | E98: CCSAP | F98: JBE | G98: Non commencé | I98: =J97 -> 42624.317 | J98: =I98+H98 -> 42624.317 | L98: Déplacement de la tache
C99: Mapping Manager Transverse avec les 6 RC*MSS* (pour délégation UWL) | E99: CCSAP | F99: JBE | G99: Non commencé | I99: =J98 -> 42624.317 | J99: =I99+H99 -> 42624.317 | L99: Déplacement de la tache
C100: Ticket 372 : Interdire Personnalisation sur les Applis Webdynpro | E100: CCSAP | F100: JBE | G100: Terminé | H100: 0.0020833333 | I100: =J99 -> 42624.317 | J100: =I100+H100 -> 42624.319 | L100: Déplacement de la tache
C101: Activation des jobs SAP | D101: 70 | E101: CC SAP | F101: JBE | G101: Terminé | H101: 0.0034722222 | I101: =J100 -> 42624.319 | J101: =I101+H101 -> 42624.322
B102: Tests fonctionnels | I102: =#REF! -> #REF! | J102: =I102+H102 -> #REF!
...

Sheet 05 - Verif_fonc_DINR
A1: Domaine | B1: Testeur | C1: Test | D1: Portail / Back End | E1: Durée prévisionnelle | F1: Statut | G1: Dry Run 1 | H1: Defect suite Dry Run 1 | I1: Dry Run 2 | J1: Go Live | K1: Post Go Live
A4: Transverse
A5: Transverse | B5: Frédérique TANNE | C5: Campagne TTA | D5: Back End | F5: A venir | G5: N/A | I5: N/A | J5: N/A | K5: 42826
A6: Transverse | B6: Frédérique TANNE | C6: Campagne TTA | D6: Portail | F6: A venir | G6: N/A | I6: N/A | J6: N/A | K6: 42826
A7: Transverse | B7: Frédérique TANNE | C7: Sélection CC | D7: Back End | F7: A venir | G7: N/A | I7: N/A | J7: N/A | K7: 42887
A8: Transverse | B8: Frédérique TANNE | C8: Sélection CC | D8: Portail | F8: A venir | G8: N/A | I8: N/A | J8: N/A | K8: 42887
A9: Transverse | B9: Frédérique TANNE | C9: Sélection CCP | D9: Back End | F9: A venir | G9: N/A | I9: N/A | J9: N/A | K9: 42887
A10: Transverse | B10: Frédérique TANNE | C10: Sélection CCP | D10: Portail | F10: A venir | G10: N/A | I10: N/A | J10: N/A | K10: 42887
A11: ERH
A12: ERH | B12: Joëlle RAHARINESY | C12: Vérification d'affichage "tous écrans" | D12: Portail | E12: 0.020833333 | F12: KO | G12: pb bandeau + situation professionnelle
A13: ERH | B13: Joëlle RAHARINESY | C13: Déconnexion manuelle et automatique | D13: Portail | E13: 0.010416667 | F13: KO | G13: pb bandeau
A14: ERH | B14: Joëlle RAHARINESY | C14: eRH - Accès Internet | D14: Portail | E14: 0.0069444444 | F14: Done | G14: 0.0069444444
A15: ERH | B15: Joëlle RAHARINESY | C15: eRH - Lien FAQ - AIDE - DEMO | D15: Portail | E15: 0.0034722222 | F15: KO | G15: pb bandeau
A16: ERH | B16: Joëlle RAHARINESY | C16: eRH - Manager - Créer une delegation | D16: Portail | E16: 0.0069444444 | F16: Done | G16: 0.0034722222
A17: ERH | B17: Olivier SCHMITT | C17: eRH - Mes messages | D17: Portail | E17: 0.0069444444 | F17: Done | G17: 0.0013888889
A18: ERH | B18: Olivier SCHMITT | C18: eRH - Mes messages - Cloture d'une tache | D18: Portail | E18: 0.0069444444 | F18: Done | G18: 0.0013888889
A19: ERH | B19: Olivier SCHMITT | C19: eRH - Salarié - Organisation du service | D19: Portail | E19: 0.0069444444 | F19: KO | G19: 05:00 pb de compil | H19: Defect 454
A20: ERH | B20: Olivier SCHMITT | C20: eRH - Attestations | D20: Portail | E20: 0.010416667 | F20: Done | G20: 0.0048611111
A21: ERH | B21: Olivier SCHMITT | C21: eRH- BSI | D21: Portail | E21: 0.0034722222 | F21: KO | H21: Defect 452
A22: ERH | B22: Olivier SCHMITT | C22: eRH- BP | D22: Portail | E22: 0.0034722222 | F22: KO | H22: Defect 452
A23: ERH | B23: Joëlle RAHARINESY | C23: eRH- EP4 et EP5 | D23: Portail | F23: A venir | G23: N/A | I23: N/A | J23: N/A | K23: Mois
A24: ERH | B24: Joëlle RAHARINESY | C24: eRH - Historique de carrière | D24: Portail | E24: 0.0034722222 | F24: KO | G24: Plantage(Defect à créer)
A25: ERH | B25: Olivier SCHMITT | C25: eRH - Données personnelles - Contacts en cas d'urgence | D25: Portail | E25: 0.0069444444 | F25: Done | H25: Defect 455 (sur format de date)
A26: ERH | B26: Olivier SCHMITT | C26: eRH - Données personnelles - Ayants Droits | D26: Portail | E26: 0.0069444444 | F26: Done | H26: Defect 456 (affichage double ":")
A27: ERH | B27: Olivier SCHMITT | C27: eRH - Contacts utiles | D27: Portail | E27: 0.0034722222 | F27: Done
A28: SAP RH
A29: SAP RH | B29: Marc DEGOBERT | C29: ZMAJ_DRT (Toutes Populations) | D29: Back End | E29: 0.020833333 | F29: Done | G29: 0.025 | L29: PB MOE - idem PROD
A30: SAP RH | B30: Marc DEGOBERT | C30: ZMAJ_USR (Toputes populations) | D30: Back End | E30: 0.020833333 | F30: Done | G30: uniquement sur MOE | I30: N/A | J30: N/A | K30: Test dans la nuit qui suit le redemarrage - Si cas à rammasser | L30: OK 00:02
A31: SAP RH | B31: Marc DEGOBERT | C31: SU01D (PPS - PPE - PPL - PNC - PNT - MOE - KLM - EXT.) | D31: Back End | E31: 0.010416667 | F31: Done | G31: 0.0083333333
A32: SAP RH | B32: Marc DEGOBERT | C32: SUIM (Rôle avec critères complexes - Documents de modification etc..) | D32: Back End | E32: 0.010416667 | F32: Done | G32: 0.0125
A33: GTA
B34: Sandrine DIETZI | C34: Saisie/Validation/Suppression & Visualisation demande d'absence dans le back end CA01 - de 4j | D34: Back end | E34: 0.0034722222 | F34: Done | G34: 0.0034722222
B35: Sandrine DIETZI | C35: Saisie/Validation/Suppression & Visualisation demande d'absence dans le front ESS (CA01/AB01/RTT) | D35: Portail | E35: 0.0069444444 | F35: Done | G35: 00:08:00 sans RTT | H35: Defect 453 (sur demande d'annulation)
B36: Sandrine DIETZI | C36: Saisie/Suppression & Visualisation demande d'absence dans le front MSS | D36: Portail | E36: 0.0069444444 | F36: Done | G36: 0.0069444444
B37: Sandrine DIETZI | C37: Contrôle des règles de prise d'absences CA01 dans le front : une seule | D37: Portail | E37: 0.0013888889 | F37: Done | G37: 0.0013888889
B38: Saléha BELLABAS | C38: Initialisation et visualisation un contingent (manuellement & par EDT) | D38: Back end | E38: 0.0034722222 | F38: Done | G38: 0.0034722222
B39: Saléha BELLABAS | C39: Recalcul du décompte de congés suite saisie d'un paiement | D39: Back end | E39: 0.0034722222 | F39: Done | G39: 0.0034722222
A40: GTA | B40: Saléha BELLABAS | C40: Contrôle du reliquat des congés lors de la saise d'une période | D40: Back end | E40: 0.0034722222 | F40: Done | G40: 0.0034722222
A41: GTA | B41: Saléha BELLABAS | C41: Saisie/Validation/Suppression & Visualisation d'une activité de mission dans le back end | D41: Back end | E41: 0.0034722222 | F41: Done | G41: 0.0069444444
A42: GTA | B42: Saléha BELLABAS | C42: Saisie/Suppression & Visualisation d'une activité de mission dans le front ESS | D42: Portail | E42: 0.0069444444 | F42: Done | G42: 0.0034722222
A43: GTA | B43: Saléha BELLABAS | C43: Saisie/Suppression & Visualisation d'une activité de mission dans le front MSS | D43: Portail | E43: 0.0069444444 | F43: Done | G43: 0.0034722222
A44: GTA | B44: Saléha BELLABAS | C44: Saisie/validation/Suppression et Visualisation d'heures compl ou supp dans le front | D44: Portail | E44: 0.0069444444 | F44: Done | G44: 0.0034722222
A45: GTA | B45: Sandrine DIETZI | C45: Gestion des badgeages en ESS (renseigner des badgeages et visualiser les compteurs débit/crédit) | D45: Portail | E45: 0.0069444444 | F45: Done | G45: 0.0069444444
A46: GTA | B46: Sandrine DIETZI | C46: Gestion des badgeages en MSS (renseigner des badgeage set visualiser les compteurs débit/crédit) | D46: Portail | E46: 0.0069444444 | F46: Done | G46: 0.0069444444
A47: GTA | B47: Saléha BELLABAS | C47: Gestion d'un PRJ (création conforme /non conforme et suppression) | D47: Back end | E47: 0.0034722222 | F47: Done | G47: 0.0069444444
A48: GTA | B48: Saléha BELLABAS | C48: Gestion d'une RPR (création/génération et suppression) | D48: Back end | E48: 0.0069444444 | F48: Done | G48: 0.0069444444
A49: GTA | B49: Saléha BELLABAS | C49: Affectation d'un horaire à un salarié PPS | D49: Back end | E49: 0.0034722222 | F49: Done | G49: 0.0034722222
A50: GTA | B50: Sandrine DIETZI | C50: Calcul du DAC PNC (Lancement EDT jusque fin avril 2017 personne avec des mois OFF et ou abs pénalisantes, congé sans solde et salarié temps complet) | D50: Back end | E50: 0.013888889 | F50: Done | G50: 0.013888889
A51: GTA | B51: Saléha BELLABAS | C51: Saisie/Validation/Suppression et Visualisation d'un remplacement dans le back end | D51: Back end | E51: 0.0069444444 | F51: Done | G51: 0.0034722222
... A56: GTA | B56: Saléha BELLABAS | C56: Vérification de quelques Reports (ZTFTM_IT7/ ZTFTM_PTBAL00 / ZTFTM_IT2003) | D56: Back end | E56: 0.0069444444 | F56: Done | G56: 0.0034722222
A57: TRAVEL
A58: TRAVEL | B58: Geneviève KERDREUX | C58: Mon profil voyageur : ajouter / modifier/ supprimer une adresse mail | D58: Portail | E58: 0.0034722222 | F58: Done | G58: 0.00069444444
A59: TRAVEL | B59: Geneviève KERDREUX | C59: Mon profil voyageur : ajouter / modifier/ supprimer un téléphone | D59: Portail | E59: 0.0034722222 | F59: Done | G59: 0.00069444444
A60: TRAVEL | B60: Geneviève KERDREUX | C60: Mon profil voyageur : ajouter / modifier/ supprimer un passeport | D60: Portail | E60: 0.0034722222 | F60: Done | G60: 0.00069444444
A61: TRAVEL | B61: Geneviève KERDREUX | C61: Planifier mes missions : Création d'une mission ( sans SBT ) Vérifier que la pop-up risque sanitaire apparait pour un pays à risque sanitaire ajouter / modifier/ supprimer un vol hors SBT ajouter / modifier/ supprimer un hotel hors SBT ajouter / modifier/ supprimer une voiture hors SBT | D61: Portail | E61: 0.0069444444 | F61: Done | G61: 0.0069444444
A62: TRAVEL | B62: Geneviève KERDREUX | C62: Planifier mes missions : Création de deux missions avec SBT : connexion au SBT réservation d'un vol SBT soumettre à validation | D62: Portail | E62: 0.0034722222 | F62: N/A | G62: SBT non accessible en PPH
A63: TRAVEL | B63: Cathy GARRIGUENC | C63: Validation/refus mission dans les eservices ( avec émission d'un vol SBT ) | D63: Portail | E63: 0.0034722222 | F63: Done | G63: SBT non accessible en PPH
A64: TRAVEL | B64: Cathy GARRIGUENC | C64: Validation mission par mail ( avec émission d'un vol SBT ) | D64: Portail | E64: 0.0034722222 | F64: N/A | G64: Mails indisponibles Modifier l'adresse du user "courrier" pour le dry run 2 => CCSAP
A65: TRAVEL | B65: Geneviève KERDREUX | C65: Exécution le job DCK_D_013OFFAPPR_EXEC (approbation déplacements offline) par SM36 | D65: Back end | E65: 0.0034722222 | F65: N/A
A66: TRAVEL | B66: Geneviève KERDREUX | C66: Modifier une des missions validées : Changement de la date fin | D66: Portail | E66: 0.0034722222 | F66: KO | G66: 0.0034722222 | H66: Erreur RFC lors de la soumission à validation de la mission validée Defect 450
A67: TRAVEL | B67: Geneviève KERDREUX | C67: Annulation des missions ( vérifier l'annulation des résa SBT ) | D67: Portail | E67: 0.0034722222 | F67: Done | G67: 0.0034722222
A68: TRAVEL | B68: Geneviève KERDREUX | C68: TP01 :création d'une mission soumise à sureté ( vérifier le WF ) ( en accord avec le service de sureté ) | D68: Back end | E68: 0.0034722222 | F68: Done | G68: 0.0034722222
A69: TRAVEL | B69: Geneviève KERDREUX | C69: Déclarer mes frais : ajouter / modifier/ supprimer un frais hotel ( tester dépassement plafond - devise JPY ) | D69: Portail | E69: 0.0034722222 | F69: KO | G69: 0.0034722222 | H69: Plantage à la modification d'une Ndf en front end Defect 451
A70: TRAVEL | B70: Geneviève KERDREUX | C70: Vérifier que le lien Site Missions & e-RH Déplacements est fonctionnel à partir de l'onglet "à lire" . | D70: Portail | E70: 0.00069444444 | F70: Done | G70: 0.00069444444
A71: TRAVEL | B71: Geneviève KERDREUX | C71: Mes adresses : ajouter / modifier/ supprimer une adresse | D71: Portail | E71: 0.0034722222 | F71: Done | G71: 0.0013888889
A72: TRAVEL | B72: Geneviève KERDREUX | C72: Mes itinéraires : ajouter / modifier/ supprimer un itinéraire | D72: Portail | E72: 0.0034722222 | F72: Done | G72: 0.0013888889
A73: TRAVEL | B73: Geneviève KERDREUX | C73: Mes déclarations : ajouter un IKS ajouter un frais soumettre à validation | D73: Portail | E73: 0.0034722222 | F73: Done | G73: 0.0034722222
A74: TRAVEL | B74: Cathy GARRIGUENC | C74: Refus de la déclaration | D74: Portail | E74: 0.0034722222 | F74: Done | G74: 0.0034722222
A75: TRAVEL | B75: Geneviève KERDREUX | C75: Scan d'une note de frais | D75: Back end | E75: 0.0034722222 | F75: Done | G75: 0.0034722222
A76: TRAVEL | B76: Geneviève KERDREUX | C76: PR05 : Contrôler les frais d'une note de frais puis liquider une note de frais ( vérifier le WF ) ( en accord avec le service de liquidation des OD ) | D76: Back end | E76: 0.0034722222 | F76: KO | G76: 0.0034722222 | H76: Plantage à la validation d'une ndf - Defect 449
A77: TRAVEL | B77: Geneviève KERDREUX | C77: PR05 : simuler une ndf qui contient des IDR plage, simuler une ndf qui contient des IDR durée. | D77: Back end | E77: 0.0034722222 | F77: Done | G77: 0.0034722222
A78: SAP FOR
A79: SAP FOR | B79: Gérard LOUM | C79: créer une session de formation avec Note) | D79: Back end | E79: 0.013888889 | F79: Done | G79: 0.0034722222
A80: SAP FOR | B80: Gérard LOUM | C80: modifier une session de formation | D80: Back end | E80: 0.010416667 | F80: Done | G80: 0.0069444444
A81: SAP FOR | B81: Gérard LOUM | C81: bloquer une session de formation | D81: Back end | E81: 0.0034722222 | F81: Done | G81: 0.0013888889
A82: SAP FOR | B82: Gérard LOUM | C82: ajouter un type de Ressource | D82: Back end | E82: 0.0034722222 | F82: Done | G82: 0.0020833333
A83: SAP FOR | B83: Gérard LOUM | C83: rechercher une session de formation dans le catalogue | D83: Back end | E83: 0.0034722222 | F83: Done | G83: 0.00040509259
A84: SAP FOR | B84: Gérard LOUM | C84: ajouter une Ressource | D84: Back end | E84: 0.0034722222 | F84: Done | G84: 0.0034722222
A85: SAP FOR | B85: Gérard LOUM | C85: désélectionner une Ressource | D85: Back end | E85: 0.0034722222 | F85: Done | G85: 0.0013888889
A86: SAP FOR | B86: Gérard LOUM | C86: créer un besoin de formation | D86: Back end | E86: 0.0069444444 | F86: Done | G86: 0.0013888889
A87: SAP FOR | B87: Gérard LOUM | C87: annuler un besoin de formation | D87: Back end | E87: 0.0034722222 | F87: Done | G87: 0.00023148148
A88: SAP FOR | B88: Gérard LOUM | C88: créer une inscription sur une session de formation | D88: Back end | E88: 0.0069444444 | F88: Done | G88: 0.00069444444
A89: SAP FOR | B89: Gérard LOUM | C89: créer une inscription en masse sur une session de formation : import du fichier traitement avec transaction ZFORM_CHARG_INSC | D89: Back end | E89: 0.0069444444 | F89: A venir | G89: Import du fichier local avec CG3Z impossible en PPH - Defect 461
A90: SAP FOR | B90: Gérard LOUM | C90: annuler une inscription | D90: Back end | E90: 0.0034722222 | F90: Done | G90: 0.00017361111
A91: SAP FOR | B91: Gérard LOUM | C91: afficher les inscriptions | D91: Back end | E91: 0.0034722222 | F91: Done | G91: 0.00023148148
A92: SAP FOR | B92: Gérard LOUM | C92: rechercher une inscription | D92: Back end | E92: 0.0034722222 | F92: Done | G92: 0.0020833333
A93: SAP FOR | B93: Gérard LOUM | C93: saisir une absence | D93: Back end | E93: 0.0034722222 | F93: Done | G93: 0.00023148148
A94: SAP FOR | B94: Gérard LOUM | C94: saisir une présence | D94: Back end | E94: 0.0034722222 | F94: Done | G94: 0.00023148148
A95: SAP FOR | B95: Gérard LOUM | C95: clôturer une session | D95: Back end | E95: 0.0034722222 | F95: Done | G95: 2.3148148e-05
A96: SAP FOR | B96: Gérard LOUM | C96: consulter l'historique de formation | D96: Back end | E96: 0.0013888889 | F96: Done | G96: 5.787037e-05
A97: SAP FOR | B97: Gérard LOUM | C97: créer un besoin avec WF4 de type CPF | D97: Portail | E97: 0.0069444444 | F97: Done | G97: 0.0013888889
A98: SAP FOR | B98: Gérard LOUM | C98: créer un besoin avec WF3 | D98: Portail | E98: 0.0069444444 | F98: Done | G98: 0.0013888889
A99: SAP FOR | B99: Gérard LOUM | C99: créer une inscription avec WF2 de type CPF | D99: Portail | E99: 0.0069444444 | F99: KO | G99: Defect 466
A100: SAP FOR | B100: Gérard LOUM | C100: créer une inscription avec WF3 | D100: Portail | E100: 0.0069444444 | F100: KO | G100: Pas d'accès au menu classification pour déclarer tâche en générale PPH new - DEFECT 466
A101: SAP FOR | B101: Gérard LOUM | C101: consulter la liste des stagiaires attendus sur une session | D101: Portail | E101: 0.0069444444 | F101: A venir | G101: onglet formateur non accessible PPH - Defect 463
A102: SAP FOR | B102: Gérard LOUM | C102: saisir une absence totale | D102: Portail | E102: 0.0069444444 | F102: A venir | G102: id
A103: SAP FOR | B103: Gérard LOUM | C103: saisir une absence partielle | D103: Portail | E103: 0.0069444444 | F103: A venir | G103: id
A104: SAP FOR | B104: Thu-Cam THUONG CONG | C104: création/modification un type de formation | D104: Back end | E104: 0.010416667 | F104: Done | G104: 0.0069444444
A105: SAP FOR | B105: Thu-Cam THUONG CONG | C105: création/modification une personne externe | D105: Back end | E105: 0.0034722222 | F105: Done | G105: 0.0013888889
A106: PRATIS
...

Sheet 06 - Tranches
C2: Tranche de numéro PS | G2: Tranche de numéro de PNC | J2: Liste infotypes | R2: Durée en sec | S2: Durée estimée
B3: 1 | C3: 1 | D3: 7329661 | F3: 1 | G3: 1 | H3: 14528273 | J3: 9008 | M3: TrancheMise à jour des tables ZTTV_Log_Matis et ZTTV_Histo_MAtis. | O3: Status | P3: Durée | Q3: Nb de batch | R3: =R5*48 -> 10921 | S3: =R3/3600 -> 3.0336111
B4: 2 | C4: =D3+1 -> 7329662 | D4: 7875083 | F4: 2 | G4: 14528274 | H4: 16212437 | J4: 9500 | L4: 1 | M4: 1 | N4: 7329661 | O4: Terminé | P4: 357 | Q4: 2
B5: 3 | C5: =D4+1 -> 7875084 | D5: 8351494 | F5: 3 | G5: 16212438 | H5: 31061521 | J5: 9501 | L5: 2 | M5: 7329662 | N5: 7475666 | O5: Terminé | P5: 200 | Q5: 1 | R5: =AVERAGE(P4:P51) -> 227.52083 | S5: Moyenne
B6: 4 | C6: =D5+1 -> 8351495 | D6: 9099913 | F6: 4 | G6: 31061522 | H6: 31842369 | J6: 9502 | L6: 3 | M6: 7475667 | N6: 7650000 | O6: Terminé | P6: 153 | Q6: 1
B7: 5 | C7: =D6+1 -> 9099914 | D7: 9301488 | F7: 5 | G7: 31842370 | H7: 32658987 | J7: 9503 | L7: 4 | M7: 7650001 | N7: 7750000 | O7: Terminé | P7: 156 | Q7: 1
B8: 6 | C8: =D7+1 -> 9301489 | D8: 9479122 | F8: 6 | G8: 32658988 | H8: 33689817 | J8: 9504 | L8: 5 | M8: 7750001 | N8: 7875083 | O8: Terminé | P8: 149 | Q8: 1
B9: 7 | C9: =D8+1 -> 9479123 | D9: 12503502 | F9: 7 | G9: 33689818 | H9: 34423579 | J9: 9506 | L9: 6 | M9: 7875084 | N9: 8351494 | O9: Terminé | P9: 256 | Q9: 2
B10: 8 | C10: =D9+1 -> 12503503 | D10: 12963947 | F10: 8 | G10: 34423580 | H10: 35390347 | J10: 9508 | L10: 7 | M10: 8351495 | N10: 9099913 | O10: Terminé | P10: 354 | Q10: 3
B11: 9 | C11: =D10+1 -> 12963948 | D11: 13479360 | F11: 9 | G11: 35390348 | H11: 35982249 | J11: 9509 | L11: 8 | M11: 9099914 | N11: 9301488 | O11: Terminé | P11: 297 | Q11: 3
B12: 10 | C12: =D11+1 -> 13479361 | D12: 13965269 | F12: 10 | G12: 35982250 | H12: 49999999 | J12: 9510 | L12: 9 | M12: 9301489 | N12: 9479122 | O12: Terminé | P12: 294 | Q12: 3
B13: 11 | C13: =D12+1 -> 13965270 | D13: 14427334 | J13: 9512 | L13: 10 | M13: 9479123 | N13: 12503502 | O13: Terminé | P13: 460 | Q13: 5
B14: 12 | C14: =D13+1 -> 14427335 | D14: 15463517 | J14: 9522 | L14: 11 | M14: 12503503 | N14: 12963947 | O14: Terminé | P14: 297 | Q14: 3
B15: 13 | C15: =D14+1 -> 15463518 | D15: 15804431 | J15: 9523 | L15: 12 | M15: 12963948 | N15: 13479360 | O15: Terminé | P15: 235 | Q15: 3
B16: 14 | C16: =D15+1 -> 15804432 | D16: 30383026 | J16: 9524 | L16: 13 | M16: 13479361 | N16: 13965269 | O16: Terminé | P16: 237 | Q16: 3
B17: 15 | C17: =D16+1 -> 30383027 | D17: 30915011 | J17: 9529 | L17: 14 | M17: 13965270 | N17: 14427334 | O17: Terminé | P17: 233 | Q17: 3
B18: 16 | C18: =D17+1 -> 30915012 | D18: 31270372 | J18: 9801 | L18: 15 | M18: 14427335 | N18: 15463517 | O18: Terminé | P18: 365 | Q18: 5
B19: 17 | C19: =D18+1 -> 31270373 | D19: 31680301 | J19: 9802 | L19: 16 | M19: 15463518 | N19: 15804431 | O19: Terminé | P19: 234 | Q19: 3
B20: 18 | C20: =D19+1 -> 31680302 | D20: 31993731 | J20: 9803 | L20: 17 | M20: 15804432 | N20: 30383026 | O20: Terminé | P20: 360 | Q20: 5
B21: 19 | C21: =D20+1 -> 31993732 | D21: 32366270 | J21: 9871 | L21: 18 | M21: 30383027 | N21: 30915011 | O21: Terminé | P21: 290 | Q21: 4
B22: 20 | C22: =D21+1 -> 32366271 | D22: 32753462 | J22: 9872 | L22: 19 | M22: 30915012 | N22: 31270372 | O22: Terminé | P22: 234 | Q22: 3
B23: 21 | C23: =D22+1 -> 32753463 | D23: 33034459 | J23: 9884 | L23: 20 | M23: 31270373 | N23: 31286337 | O23: Terminé | P23: 107 | Q23: 1
B24: 22 | C24: =D23+1 -> 33034460 | D24: 33443172 | J24: 9891 | L24: 21 | M24: 31286338 | N24: 31287338 | O24: Terminé | P24: 102 | Q24: 1
... B27: 25 | C27: =D26+1 -> 34251408 | D27: 34921717 | J27: 9894 | L27: 24 | M27: 31291187 | N27: 31680301 | O27: Terminé | P27: 231 | Q27: 3
B28: 26 | C28: =D27+1 -> 34921718 | D28: 35558075 | L28: 25 | M28: 31680302 | N28: 31993731 | O28: Terminé | P28: 167 | Q28: 2
B29: 27 | C29: =D28+1 -> 35558076 | D29: 40058774 | L29: 26 | M29: 31993732 | N29: 32366270 | O29: Terminé | P29: 236 | Q29: 3
B30: 28 | C30: =D29+1 -> 40058775 | D30: 40361801 | L30: 27 | M30: 32366271 | N30: 32753462 | O30: Terminé | P30: 237 | Q30: 3
B31: 29 | C31: =D30+1 -> 40361802 | D31: 40685840 | L31: 28 | M31: 32753463 | N31: 33034459 | O31: Terminé | P31: 233 | Q31: 3
B32: 30 | C32: =D31+1 -> 40685841 | D32: 41024229 | L32: 29 | M32: 33034460 | N32: 33443172 | O32: Terminé | P32: 296 | Q32: 4
B33: 31 | C33: =D32+1 -> 41024230 | D33: 41684435 | L33: 30 | M33: 33443173 | N33: 33830162 | O33: Terminé | P33: 298 | Q33: 4
B34: 32 | C34: =D33+1 -> 41684436 | D34: 49999999 | L34: 31 | M34: 33830163 | N34: 34251407 | O34: Terminé | P34: 298 | Q34: 4
L35: 32 | M35: 34251408 | N35: 34644457 | O35: Terminé | P35: 170 | Q35: 2
L36: 33 | M36: 34644458 | N36: 34654457 | O36: Terminé | P36: 104 | Q36: 1
L37: 34 | M37: 34654458 | N37: 34664457 | O37: Terminé | P37: 103 | Q37: 1
L38: 35 | M38: 34664458 | N38: 34674457 | O38: Terminé | P38: 103 | Q38: 1
L39: 36 | M39: 34674458 | N39: 34684457 | O39: Terminé | P39: 103 | Q39: 1
L40: 37 | M40: 34684458 | N40: 34694457 | O40: Terminé | P40: 103 | Q40: 1
L41: 38 | M41: 34694458 | N41: 34704457 | O41: Terminé | P41: 102 | Q41: 1
L42: 39 | M42: 34704458 | N42: 34712457 | O42: Terminé | P42: 102 | Q42: 1
L43: 40 | M43: 34712458 | N43: 34722461 | O43: Terminé | P43: 102 | Q43: 1
L44: 41 | M44: 34722462 | N44: 34921717 | O44: Terminé | P44: 104 | Q44: 1
L45: 42 | M45: 34921718 | N45: 35558075 | O45: Terminé | P45: 294 | Q45: 4
L46: 43 | M46: 35558076 | N46: 40058774 | O46: Terminé | P46: 357 | Q46: 5
... L51: 48 | M51: 41684436 | N51: 49999999 | O51: Terminé | P51: 473 | Q51: 7

Sheet 07 - Liste d'OTs
B2: Liste 1 - SPAU + 1° report de maintenance | G2: Liste 2 - MAJ cluster TE | L2: Liste 3 - Autorisation + Defects + 2° report de maintenance | O2: Liste 4 | R2: Liste 5 | T2: Liste 6 | V2: Liste 7 | X2: Liste 8 | Z2: Liste 9 | AB2: Liste 10
B3: DVHK960032 | C3: 4119573 | D3: P-UPECCHR-MOVE4HR-SPAU-01 | E3: code 8 attendu | G3: DVHK960228 | H3: 4119573 | I3: P-UPECCHR-MOVE4HR-ZTV_MAJ_CLUSTER_TE-01 | J3: code 8 attendu | L3: DVHK960995 | M3: code 8 attendu | O3: DVHK960389 | R3: DVHK960494 | T3: DVHK960594 | V3: DVHK960697 | X3: DVHK960799 | Z3: DVHK960931 | AB3: DVHK960481
B4: DVHK960220 | C4: 4119573 | D4: P-UPECCHR-MOVE4HR-SPAU-02 | G4: DVHK960232 | H4: 4119573 | I4: P-UPECCHR-MOVE4HR-ZTV_MAJ_CLUSTER_TE-02 | L4: DVHK960142 | M4: code 8 attendu | O4: DVHK960278 | R4: DVHK960496 | T4: DVHK960475 | V4: DVHK960701 | X4: DVHK960793 | Z4: DVHK960933 | AB4: DVHK960482
B5: DVHK960105 | C5: 4119573 | D5: P-UPECCHR-MOVE4HR-Upgrade parametrage-01 | G5: DVHK960235 | H5: 4119573 | I5: P-UPECCHR-MOVE4HR-ZTV_EXTRACT_CLUSTER_TE-01 | L5: DVHK960257 | O5: DVHK960317 | R5: DVHK960498 | T5: DVHK960573 | V5: DVHK960542 | X5: DVHK960804 | Z5: DVHK960888 | AB5: DVHK960585
B6: DVHK960036 | C6: 4119573 | D6: P-UPECCHR-MOVE4HR-Corrections Panaya-01 | E6: code 8 attendu | G6: DVHK960239 | H6: 4119573 | I6: P-UPECCHR-MOVE4HR-ZTV_EXTRACT_CLUSTER_TE-02 | L6: DVHK960253 | O6: DVHK960321 | R6: DVHK960500 | T6: DVHK960586 | V6: DVHK960715 | X6: DVHK960806 | Z6: DVHK960955 | AB6: DVHK960487
B7: DVHK960222 | C7: 4119573 | D7: P-UPECCHR-MOVE4HR-SPAU-03 | G7: DVHK960285 | H7: T367844 | I7: P-UPECCHR-MOVE4HR-ZTV_EXTRACT_CLUSTER_TE-03 | L7: DVHK960259 | O7: DVHK960313 | R7: DVHK960046 | T7: DVHK960626 | V7: DVHK960657 | X7: DVHK960808 | Z7: DVHK960959 | AB7: DVHK960535
B8: DVHK960206 | G8: DVHK960305 | H8: T367844 | I8: P-UPECCHR-MOVE4HR-ZTV_EXTRACT_CLUSTER_TE-04 | L8: DVHK960271 | O8: DVHK960325 | P8: code 8 attendu | R8: DVHK960502 | T8: DVHK960608 | V8: DVHK960418 | X8: DVHK960814 | Z8: TV1K900044 | AB8: DVHK960536
B9: DVHK960136 | L9: DVHK960127 | O9: DVHK960382 | R9: DVHK960504 | T9: DVHK960610 | V9: DVHK960651 | X9: DVHK960816 | Z9: TV1K900751 | AB9: DVHK960538
B10: DVHK960144 | L10: DVHK960261 | O10: DVHK960325 | R10: DVHK960524 | T10: DVHK960614 | V10: DVHK960558 | X10: DVHK960789 | Z10: DVHK960967 | AB10: DVHK960612
B11: DVHK960200 | L11: DVHK960245 | O11: DVHK960406 | R11: DVHK960506 | T11: DVHK960616 | V11: DVHK960719 | X11: DVHK960787 | Z11: DVHK960969 | AB11: DVHK960628
B12: DVHK960202 | L12: DVHK960249 | O12: DVHK960402 | R12: DVHK960508 | T12: DVHK960618 | V12: DVHK960717 | X12: DVHK960791 | Z12: DVHK960870 | AB12: DVHK960669
B13: DVHK960208 | L13: DVHK960251 | O13: DVHK960404 | R13: DVHK960510 | T13: DVHK960583 | V13: DVHK960649 | X13: DVHK960795 | Z13: DVHK960979 | AB13: DVHK960671
B14: DVHK960146 | L14: DVHK960255 | O14: DVHK960263 | R14: DVHK960516 | T14: DVHK960620 | V14: DVHK960550 | X14: DVHK960802 | Z14: DVHK960975 | AB14: DVHK960864
B15: DVHK960140 | L15: DVHK960247 | O15: DVHK960323 | R15: DVHK960300 | T15: DVHK960622 | V15: DVHK960685 | X15: DVHK960818 | Z15: DVHK960977 | AB15: DVHK960771
B16: DVHK960148 | L16: DVHK960263 | O16: DVHK960319 | R16: DVHK960422 | T16: DVHK960624 | V16: DVHK960581 | X16: DVHK960820 | Z16: DVHK960985
B17: DVHK960150 | L17: DVHK960237 | O17: DVHK960387 | R17: DVHK960489 | T17: DVHK960596 | V17: DVHK960655 | X17: DVHK960822 | Z17: DVHK960989
B18: DVHK960164 | L18: DVHK960130 | O18: DVHK960424 | R18: DVHK960313 | T18: DVHK960633 | V18: DVHK960705 | X18: DVHK960826 | Z18: DVHK960991
B19: DVHK960152 | L19: DVHK960180 | O19: DVHK960378 | R19: DVHK960520 | T19: DVHK960631 | V19: DVHK960721 | X19: DVHK960879 | Z19: DVHK961005 | AB19: E8BK900024
B20: DVHK960160 | L20: DVHK960182 | O20: DVHK960430 | R20: DVHK960411 | T20: DVHK960635 | V20: DVHK960699 | X20: DVHK960828
B21: DVHK960196 | L21: DVHK960184 | O21: DVHK960433 | R21: DVHK960393 | T21: DVHK960637 | V21: DVHK960725 | X21: DVHK960898
B22: DVHK960172 | L22: DVHK960186 | O22: DVHK960359 | R22: DVHK960522 | T22: DVHK960639 | V22: DVHK960727 | X22: DVHK960919
B23: DVHK960156 | L23: DVHK960188 | O23: DVHK960303 | R23: DVHK960469 | T23: DVHK960606 | V23: DVHK960729 | X23: DVHK960540
B24: DVHK960166 | L24: DVHK960190 | O24: DVHK960374 | R24: DVHK960471 | T24: DVHK960641 | V24: DVHK960731 | X24: DVHK960265
B25: DVHK960154 | L25: DVHK960192 | O25: DVHK960440 | R25: DVHK960518 | T25: DVHK960598 | V25: DVHK960736 | X25: DVHK960267
B26: DVHK960210 | L26: DVHK960125 | O26: DVHK960376 | R26: DVHK960528 | T26: DVHK960659 | V26: DVHK960703 | X26: DVHK960830
B27: DVHK960168 | L27: DVHK960298 | O27: DVHK960450 | R27: DVHK960530 | T27: DVHK960600 | V27: DVHK960740 | X27: DVHK960832
B28: DVHK960162 | L28: DVHK960331 | O28: DVHK960452 | R28: DVHK960532 | T28: DVHK960643 | V28: DVHK960742 | X28: DVHK960834
B29: DVHK960158 | L29: DVHK960315 | O29: DVHK960454 | R29: DVHK960552 | T29: DVHK960685 | V29: DVHK960738 | X29: DVHK960838
B30: DVHK960213 | L30: DVHK960361 | O30: DVHK960442 | R30: DVHK960544 | T30: DVHK960581 | V30: DVHK960744 | X30: DVHK960840
B31: DVHK960170 | L31: DVHK960273 | O31: DVHK960456 | R31: DVHK960556 | T31: DVHK960663 | V31: DVHK960661 | X31: DVHK960842
... B33: DVHK960230 | L33: DVHK960363 | O33: DVHK960478 | R33: DVHK960560 | T33: DVHK960689 | V33: DVHK960645 | X33: DVHK960848
L34: DVHK960339 | O34: DVHK960446 | R34: DVHK960554 | T34: DVHK960691 | V34: DVHK960748 | X34: DVHK960850
L35: DVHK960287 | O35: DVHK960448 | R35: DVHK960565 | T35: DVHK960676 | V35: DVHK960752 | X35: DVHK960852
L36: DVHK960341 | O36: DVHK960483 | R36: DVHK960473 | T36: DVHK960665 | V36: DVHK960755 | X36: DVHK960854
L37: DVHK960343 | O37: DVHK960459 | R37: DVHK960567 | T37: DVHK960678 | V37: DVHK960757 | X37: DVHK960858
L38: DVHK960345 | O38: DVHK960461 | R38: DVHK960569 | T38: DVHK960680 | V38: DVHK960759 | X38: DVHK960912
L39: DVHK960347 | O39: DVHK960463 | R39: DVHK960571 | T39: DVHK960707 | V39: DVHK960761 | X39: DVHK960903
L40: DVHK960368 | O40: DVHK960465 | R40: DVHK960575 | T40: DVHK960709 | V40: DVHK960765 | X40: DVHK960905
L41: DVHK960370 | O41: DVHK960467 | R41: DVHK960579 | T41: DVHK960711 | V41: DVHK960767 | X41: DVHK960907
L42: DVHK960349 | O42: DVHK960512 | R42: DVHK960577 | T42: DVHK960713 | V42: DVHK960769 | X42: DVHK960917
L43: DVHK960384 | R43: DVHK960588 | T43: DVHK960682 | V43: DVHK960134 | X43: DVHK960921
L44: DVHK960391 | R44: DVHK960590 | V44: DVHK960775 | X44: DVHK960647
L45: DVHK960351 | R45: DVHK960592 | V45: DVHK960773 | X45: DVHK960929
L46: DVHK960353 | R46: DVHK960604 | V46: DVHK960777
L47: DVHK960380 | R47: DVHK960602 | V47: DVHK960779
L48: DVHK960355 | V48: DVHK960781
L49: DVHK960397 | V49: DVHK960783
L50: DVHK960408 | V50: DVHK960785
L51: DVHK960357

Sheet Ots consolidés controle 
A1: DVHK960799
A2: DVHK960793
A3: DVHK960804
A4: DVHK960806
A5: DVHK960808
A6: DVHK960814
A7: DVHK960816
A8: DVHK960789
A9: DVHK960787
A10: DVHK960791
A11: DVHK960795
A12: DVHK960802
... A333: E8BK900024

Sheet Roll Back
C1: ACTIVITY | D1: TASK ID | E1: Resp. dept. | F1: ACTOR | G1: Status | H1: Duration | I1: Planned Start | J1: Planned End | K1: Dependency | L1: Comments
A2: Déclanchement RollBacl
B3: Restauration BDD
C4: RollBack - Restauration BDD avant DownTime | E4: AF | F4: Paul ANDRE | H4: 0.25
B9: Restauration Binaires SAP | E9: DI.NR / AMO | H9: =SUM(H10:H20) -> 0.20138889
C10: Rollback - Sauvegarde binaires ECC5 DB/CI | E10: CGI | F10: David | H10: 0.020833333 | L10: Restaurer (tar) /usr/sap Restaurer (tar) /sapmnt Restaurer (tar) les fichiers profils (.*) /home/prhadm Restaurer (tar) les fichiers profils (.*) /home/oraprh OU /oracle/PRH (fichiers profils à la racine)
C11: Rollback - Sauvegarde binaires ECC5 AS#1 | E11: CGI | F11: David | H11: 0.020833333 | L11: Restaurer (tar) /usr/sap Restaurer (tar) /sapmnt Restaurer (tar) les fichiers profils (.*) /home/prhadm
C12: Rollback - Sauvegarde binaires ECC5 AS#2 | E12: CGI | F12: David | H12: 0.020833333 | L12: Restaurer (tar) /usr/sap Restaurer (tar) /sapmnt Restaurer (tar) les fichiers profils (.*) /home/prhadm
C13: Rollback - Sauvegarde binaires ECC5 AS#3 | E13: CGI | F13: David | H13: 0.020833333 | L13: Restaurer (tar) /usr/sap Restaurer (tar) /sapmnt Restaurer (tar) les fichiers profils (.*) /home/prhadm
C14: Rollback - Sauvegarde binaires ECC5 AS#4 | E14: CGI | F14: David | H14: 0.020833333 | L14: Restaurer (tar) /usr/sap Restaurer (tar) /sapmnt Restaurer (tar) les fichiers profils (.*) /home/prhadm
C15: Rollback - Sauvegarde binaires ECC5 AS#5 | E15: CGI | F15: David | H15: 0.020833333 | L15: Restaurer (tar) /usr/sap Restaurer (tar) /sapmnt Restaurer (tar) les fichiers profils (.*) /home/prhadm
C16: Rollback - Sauvegarde binaires ECC5 AS#6 | E16: CGI | F16: David | H16: 0.020833333 | L16: Restaurer (tar) /usr/sap Restaurer (tar) /sapmnt Restaurer (tar) les fichiers profils (.*) /home/prhadm
C17: Rollback - Sauvegarde binaires ECC5 AS#7 | E17: CGI | F17: David | H17: 0.020833333 | L17: Restaurer (tar) /usr/sap Restaurer (tar) /sapmnt Restaurer (tar) les fichiers profils (.*) /home/prhadm
C18: Rollback - Sauvegarde binaires ECC5 AS#8 | E18: CGI | F18: David | H18: 0.020833333 | L18: Restaurer (tar) /usr/sap Restaurer (tar) /sapmnt Restaurer (tar) les fichiers profils (.*) /home/prhadm
C19: Rollback - Redémarrage SAP | E19: CGI | F19: David | H19: 0.0069444444
C20: Rollback - Test technique avec EP | E20: AF | H20: 0.0069444444 | L20: Support CGI/David
B22: Post-processing frontend
B27: Reprise Nuit Applicative | H27: =SUM(H28:H43) -> 0.10833333
C28: Déblocage des users techniques interface (MAESTRO, ALE*) | E28: CCSAP | F28: JBE | G28: Non commencé | H28: 0.0020833333
C29: Déblocage partenaire Logique PRH200 sur Corporate (PRD) | E29: CCSAP | F29: JBE | G29: Non commencé | H29: 0.0020833333
C30: Intégrer les Banques en provenance de Corporate dans PRH200 | E30: CCSAP | F30: JBE | G30: Non commencé | H30: 0.0034722222
C31: Cancel de tous les flux en attente (en TO BEGIN) | E31: AOS Flux | F31: Marc Amaury SALMON | G31: Non commencé | H31: 0.0069444444
C32: Suspension des jobs SAP | D32: 70 | E32: CC SAP | F32: JBE | G32: Non commencé | H32: 0.0034722222
C33: Relance des transferts sur l'ensemble des jours d'arret | E33: AOS Flux | F33: Marc Amaury SALMON | G33: Non commencé | H33: 0.0069444444
C34: Réouverture des batchs | E34: C2B | G34: Non commencé | H34: 0.0069444444
C35: Controler le Fence = 0 (TWS) | E35: DI.NR | F35: Pavel | G35: Non commencé | H35: 0.0069444444
C36: Lancement des interfaces forcées (3-4 à détailler depuis fichier Théo) Time port | G36: Non commencé
C37: Lancer le job d'extraction (si problèmes nous avons jusqu'au lundi pour le lancer) | E37: DWHCORH | F37: Sandrine | G37: Non commencé | H37: 0.010416667
C38: tâches dans le chrono (vérifier complétude) | E38: TimePort Gestor | F38: Pavel+ Damien | G38: Non commencé | H38: 0.020833333
C39: Prévenir: AMO SCGP: C Dray Gaston, MOE Cathy Parnot et Corinne Gambino pour que les services soient redémarrés. Leur confirmer que le 1er fichier envoyé arrivera Mardi à 1h du matin. | E39: SCGP SERVEUR GP | F39: Olivier | G39: Non commencé | H39: 0.010416667
C40: Déblocage de tous les utilisateurs | F40: Julien | G40: Non commencé | H40: 0.0069444444
C41: Communication sur réouverture système | F41: Sophie | G41: Non commencé | H41: 0.0069444444
C42: Modification/suspension des messages e-services, | F42: Thierry MARCHAND | G42: Non commencé | H42: 0.0069444444
C43: Modification/suspension des messages intralignes | F43: Sophie | G43: Non commencé | H43: 0.0069444444
